{
    "packet": [{
            "lenght": "752",
            "Layer ETH": "\nDestination: 44:39:c4:59:3b:02\n\n\nAddress: 44:39:c4:59:3b:02\n\n\n.... ..0. .... .... .... .... = LG bit: Globally unique address (factory default)\n\n\n.... ...0 .... .... .... .... = IG bit: Individual address (unicast)\n\n\nSource: 90:98:38:97:e0:a0\n\n\n.... ..0. .... .... .... .... = LG bit: Globally unique address (factory default)\n\n\n.... ...0 .... .... .... .... = IG bit: Individual address (unicast)\n\n\nType: ARP (0x0806)\n\n\nPadding: 000000000000000000000000000000000000\n\n\nAddress: 90:98:38:97:e0:a0\n\n\n",
            "Layer IP": "\n0100 .... = Version: 4\n\n\n.... 0101 = Header Length: 20 bytes (5)\n\n\nDifferentiated Services Field: 0xa0 (DSCP: CS5, ECN: Not-ECT)\n\n\n1010 00.. = Differentiated Services Codepoint: Class Selector 5 (40)\n\n\n.... ..00 = Explicit Congestion Notification: Not ECN-Capable Transport (0)\n\n\nTotal Length: 738\n\n\nIdentification: 0x4e03 (19971)\n\n\nFlags: 0x00\n\n\n0... .... = Reserved bit: Not set\n\n\n.0.. .... = Don't fragment: Not set\n\n\n..0. .... = More fragments: Not set\n\n\nFragment Offset: 0\n\n\nTime to Live: 64\n\n\nProtocol: UDP (17)\n\n\nHeader Checksum: 0x67b8 [validation disabled]\n\n\nHeader checksum status: Unverified\n\n\nSource Address: 192.168.1.8\n\n\nDestination Address: 255.255.255.255\n\n\n",
            "Layer UDP": "\nSource Port: 56465\n\n\nDestination Port: 29810\n\n\nLength: 718\n\n\nChecksum: 0x45b1 [unverified]\n\n\nChecksum Status: Unverified\n\n\nStream index: 0\n\n\nTimestamps\n\n\nTime since first frame: 0.000000000 seconds\n\n\nTime since previous frame: 0.000000000 seconds\n\n\nUDP payload (710 bytes)\n\n\nDATAPacket (Length: 60)\n\n\n",
            "Layer ARP": "\nHardware type: Ethernet (1)\n\n\nProtocol type: IPv4 (0x0800)\n\n\nHardware size: 6\n\n\nProtocol size: 4\n\n\nOpcode: request (1)\n\n\nSender MAC address: 90:98:38:97:e0:a0\n\n\nSender IP address: 192.168.1.1\n\n\nTarget MAC address: 00:00:00:00:00:00\n\n\nTarget IP address: 192.168.1.147\n\n\n",
            "Layer TLS": "\nTLSv1.2 Record Layer: Application Data Protocol: http-over-tls\n\n\nContent Type: Application Data (23)\n\n\nVersion: TLS 1.2 (0x0303)\n\n\nLength: 1109\n\n\nEncrypted Application Data: 594a92dd56bc566c48f083536a36a2961e084d700d4da6d7f8b71c6c1b4a2e14863e108c\u2026\n\n\nApplication Data Protocol: http-over-tls\n\n\n",
            "Layer DNS": "\nTransaction ID: 0x440d\n\n\nFlags: 0x0100 Standard query\n\n\n0... .... .... .... = Response: Message is a query\n\n\n.000 0... .... .... = Opcode: Standard query (0)\n\n\n.... ..0. .... .... = Truncated: Message is not truncated\n\n\n.... ...1 .... .... = Recursion desired: Do query recursively\n\n\n.... .... .0.. .... = Z: reserved (0)\n\n\n.... .... ...0 .... = Non-authenticated data: Unacceptable\n\n\nQuestions: 1\n\n\nAnswer RRs: 0\n\n\nAuthority RRs: 0\n\n\nAdditional RRs: 0\n\n\nQueries\n\n\nName: clients4.google.com\n\n\nName Length: 19\n\n\nLabel Count: 3\n\n\nType: A (Host Address) (1)\n\n\nClass: IN (0x0001)\n\n\nclients4.google.com: type A, class IN\n\n\n",
            "Layer TCP": "\nSource Port: 64372\n\n\nDestination Port: 443\n\n\nStream index: 0\n\n\nTCP Segment Len: 807\n\n\nSequence Number: 1413    (relative sequence number)\n\n\nSequence Number (raw): 3437899461\n\n\nNext Sequence Number: 2220    (relative sequence number)\n\n\nAcknowledgment Number: 1    (relative ack number)\n\n\nAcknowledgment number (raw): 3848498196\n\n\n0101 .... = Header Length: 20 bytes (5)\n\n\nFlags: 0x018 (PSH, ACK)\n\n\n000. .... .... = Reserved: Not set\n\n\n...0 .... .... = Nonce: Not set\n\n\n.... 0... .... = Congestion Window Reduced (CWR): Not set\n\n\n.... .0.. .... = ECN-Echo: Not set\n\n\n.... ..0. .... = Urgent: Not set\n\n\n.... ...1 .... = Acknowledgment: Set\n\n\n.... .... 1... = Push: Set\n\n\n.... .... .0.. = Reset: Not set\n\n\n.... .... ..0. = Syn: Not set\n\n\n.... .... ...0 = Fin: Not set\n\n\nTCP Flags: \u00b7\u00b7\u00b7\u00b7\u00b7\u00b7\u00b7AP\u00b7\u00b7\u00b7\n\n\nWindow: 511\n\n\nCalculated window size: 511\n\n\nWindow size scaling factor: -1 (unknown)\n\n\nChecksum: 0xef76 [unverified]\n\n\nChecksum Status: Unverified\n\n\nUrgent Pointer: 0\n\n\nSEQ/ACK analysis\n\n\nBytes in flight: 2219\n\n\nBytes sent since last PSH flag: 2219\n\n\nTimestamps\n\n\nTime since first frame in this TCP stream: 0.000001000 seconds\n\n\nTime since previous frame in this TCP stream: 0.000001000 seconds\n\n\nTCP payload (807 bytes)\n\n\nTCP segment data (807 bytes)\n\n\nDATALayer TLS:\n\n\nTLSv1.2 Record Layer: Application Data Protocol: http-over-tls\n\n\nContent Type: Application Data (23)\n\n\nVersion: TLS 1.2 (0x0303)\n\n\nLength: 2214\n\n\nEncrypted Application Data: e32517702f70ffb4793178ff6dad548017914d511926cc7a31a0bfb9e97bf7be8f117c5f\u2026\n\n\nApplication Data Protocol: http-over-tls\n\n\n"

        },
        {
            "lenght": "42",
            "Layer ETH": "\nDestination: 90:98:38:97:e0:a0\n\n\nAddress: 90:98:38:97:e0:a0\n\n\n.... ..0. .... .... .... .... = LG bit: Globally unique address (factory default)\n\n\n.... ...0 .... .... .... .... = IG bit: Individual address (unicast)\n\n\nSource: 44:39:c4:59:3b:02\n\n\n.... ..0. .... .... .... .... = LG bit: Globally unique address (factory default)\n\n\n.... ...0 .... .... .... .... = IG bit: Individual address (unicast)\n\n\nType: ARP (0x0806)\n\n\nAddress: 44:39:c4:59:3b:02\n\n\n",
            "Layer ARP": "\nHardware type: Ethernet (1)\n\n\nProtocol type: IPv4 (0x0800)\n\n\nHardware size: 6\n\n\nProtocol size: 4\n\n\nOpcode: reply (2)\n\n\nSender MAC address: 44:39:c4:59:3b:02\n\n\nSender IP address: 192.168.1.147\n\n\nTarget MAC address: 90:98:38:97:e0:a0\n\n\nTarget IP address: 192.168.1.1\n\n\n"
        },
        {
            "lenght": "1466",
            "Layer ETH": "\nDestination: 90:98:38:97:e0:a0\n\n\nAddress: 90:98:38:97:e0:a0\n\n\n.... ..0. .... .... .... .... = LG bit: Globally unique address (factory default)\n\n\n.... ...0 .... .... .... .... = IG bit: Individual address (unicast)\n\n\nSource: 44:39:c4:59:3b:02\n\n\n.... ..0. .... .... .... .... = LG bit: Globally unique address (factory default)\n\n\n.... ...0 .... .... .... .... = IG bit: Individual address (unicast)\n\n\nType: IPv4 (0x0800)\n\n\nAddress: 44:39:c4:59:3b:02\n\n\n",
            "Layer IP": "\n0100 .... = Version: 4\n\n\n.... 0101 = Header Length: 20 bytes (5)\n\n\nDifferentiated Services Field: 0x00 (DSCP: CS0, ECN: Not-ECT)\n\n\n0000 00.. = Differentiated Services Codepoint: Default (0)\n\n\n.... ..00 = Explicit Congestion Notification: Not ECN-Capable Transport (0)\n\n\nTotal Length: 1452\n\n\nIdentification: 0xe2d1 (58065)\n\n\nFlags: 0x40, Don't fragment\n\n\n0... .... = Reserved bit: Not set\n\n\n.1.. .... = Don't fragment: Set\n\n\n..0. .... = More fragments: Not set\n\n\nFragment Offset: 0\n\n\nTime to Live: 128\n\n\nProtocol: TCP (6)\n\n\nHeader Checksum: 0xeecf [validation disabled]\n\n\nHeader checksum status: Unverified\n\n\nSource Address: 192.168.1.147\n\n\nDestination Address: 81.192.15.175\n\n\n",
            "Layer TCP": "\nSource Port: 64372\n\n\nDestination Port: 443\n\n\nStream index: 0\n\n\nTCP Segment Len: 1412\n\n\nSequence Number: 1    (relative sequence number)\n\n\nSequence Number (raw): 3437898049\n\n\nNext Sequence Number: 1413    (relative sequence number)\n\n\nAcknowledgment Number: 1    (relative ack number)\n\n\nAcknowledgment number (raw): 3848498196\n\n\n0101 .... = Header Length: 20 bytes (5)\n\n\nFlags: 0x010 (ACK)\n\n\n000. .... .... = Reserved: Not set\n\n\n...0 .... .... = Nonce: Not set\n\n\n.... 0... .... = Congestion Window Reduced (CWR): Not set\n\n\n.... .0.. .... = ECN-Echo: Not set\n\n\n.... ..0. .... = Urgent: Not set\n\n\n.... ...1 .... = Acknowledgment: Set\n\n\n.... .... 0... = Push: Not set\n\n\n.... .... .0.. = Reset: Not set\n\n\n.... .... ..0. = Syn: Not set\n\n\n.... .... ...0 = Fin: Not set\n\n\nTCP Flags: \u00b7\u00b7\u00b7\u00b7\u00b7\u00b7\u00b7A\u00b7\u00b7\u00b7\u00b7\n\n\nWindow: 511\n\n\nCalculated window size: 511\n\n\nWindow size scaling factor: -1 (unknown)\n\n\nChecksum: 0xf205 [unverified]\n\n\nChecksum Status: Unverified\n\n\nUrgent Pointer: 0\n\n\nSEQ/ACK analysis\n\n\nBytes in flight: 1412\n\n\nBytes sent since last PSH flag: 1412\n\n\nTimestamps\n\n\nTime since first frame in this TCP stream: 0.000000000 seconds\n\n\nTime since previous frame in this TCP stream: 0.000000000 seconds\n\n\nTCP payload (1412 bytes)\n\n\nTCP segment data (1412 bytes)\n\n\n",
            "Layer TLS": "\n"
        },
        {
            "lenght": "861",
            "Layer ETH": "\nDestination: 90:98:38:97:e0:a0\n\n\nAddress: 90:98:38:97:e0:a0\n\n\n.... ..0. .... .... .... .... = LG bit: Globally unique address (factory default)\n\n\n.... ...0 .... .... .... .... = IG bit: Individual address (unicast)\n\n\nSource: 44:39:c4:59:3b:02\n\n\n.... ..0. .... .... .... .... = LG bit: Globally unique address (factory default)\n\n\n.... ...0 .... .... .... .... = IG bit: Individual address (unicast)\n\n\nType: IPv4 (0x0800)\n\n\nAddress: 44:39:c4:59:3b:02\n\n\n",
            "Layer IP": "\n0100 .... = Version: 4\n\n\n.... 0101 = Header Length: 20 bytes (5)\n\n\nDifferentiated Services Field: 0x00 (DSCP: CS0, ECN: Not-ECT)\n\n\n0000 00.. = Differentiated Services Codepoint: Default (0)\n\n\n.... ..00 = Explicit Congestion Notification: Not ECN-Capable Transport (0)\n\n\nTotal Length: 847\n\n\nIdentification: 0xe2d2 (58066)\n\n\nFlags: 0x40, Don't fragment\n\n\n0... .... = Reserved bit: Not set\n\n\n.1.. .... = Don't fragment: Set\n\n\n..0. .... = More fragments: Not set\n\n\nFragment Offset: 0\n\n\nTime to Live: 128\n\n\nProtocol: TCP (6)\n\n\nHeader Checksum: 0xf12b [validation disabled]\n\n\nHeader checksum status: Unverified\n\n\nSource Address: 192.168.1.147\n\n\nDestination Address: 81.192.15.175\n\n\n",
            "Layer TCP": "\nSource Port: 64372\n\n\nDestination Port: 443\n\n\nStream index: 0\n\n\nTCP Segment Len: 807\n\n\nSequence Number: 1413    (relative sequence number)\n\n\nSequence Number (raw): 3437899461\n\n\nNext Sequence Number: 2220    (relative sequence number)\n\n\nAcknowledgment Number: 1    (relative ack number)\n\n\nAcknowledgment number (raw): 3848498196\n\n\n0101 .... = Header Length: 20 bytes (5)\n\n\nFlags: 0x018 (PSH, ACK)\n\n\n000. .... .... = Reserved: Not set\n\n\n...0 .... .... = Nonce: Not set\n\n\n.... 0... .... = Congestion Window Reduced (CWR): Not set\n\n\n.... .0.. .... = ECN-Echo: Not set\n\n\n.... ..0. .... = Urgent: Not set\n\n\n.... ...1 .... = Acknowledgment: Set\n\n\n.... .... 1... = Push: Set\n\n\n.... .... .0.. = Reset: Not set\n\n\n.... .... ..0. = Syn: Not set\n\n\n.... .... ...0 = Fin: Not set\n\n\nTCP Flags: \u00b7\u00b7\u00b7\u00b7\u00b7\u00b7\u00b7AP\u00b7\u00b7\u00b7\n\n\nWindow: 511\n\n\nCalculated window size: 511\n\n\nWindow size scaling factor: -1 (unknown)\n\n\nChecksum: 0xef76 [unverified]\n\n\nChecksum Status: Unverified\n\n\nUrgent Pointer: 0\n\n\nSEQ/ACK analysis\n\n\nBytes in flight: 2219\n\n\nBytes sent since last PSH flag: 2219\n\n\nTimestamps\n\n\nTime since first frame in this TCP stream: 0.000001000 seconds\n\n\nTime since previous frame in this TCP stream: 0.000001000 seconds\n\n\nTCP payload (807 bytes)\n\n\nTCP segment data (807 bytes)\n\n\nDATALayer TLS:\n\n\nTLSv1.2 Record Layer: Application Data Protocol: http-over-tls\n\n\nContent Type: Application Data (23)\n\n\nVersion: TLS 1.2 (0x0303)\n\n\nLength: 2214\n\n\nEncrypted Application Data: e32517702f70ffb4793178ff6dad548017914d511926cc7a31a0bfb9e97bf7be8f117c5f\u2026\n\n\nApplication Data Protocol: http-over-tls\n\n\n"
        },
        {
            "lenght": "78",
            "Layer ETH": "\nDestination: 90:98:38:97:e0:a0\n\n\nAddress: 90:98:38:97:e0:a0\n\n\n.... ..0. .... .... .... .... = LG bit: Globally unique address (factory default)\n\n\n.... ...0 .... .... .... .... = IG bit: Individual address (unicast)\n\n\nSource: 44:39:c4:59:3b:02\n\n\n.... ..0. .... .... .... .... = LG bit: Globally unique address (factory default)\n\n\n.... ...0 .... .... .... .... = IG bit: Individual address (unicast)\n\n\nType: IPv4 (0x0800)\n\n\nAddress: 44:39:c4:59:3b:02\n\n\n",
            "Layer IP": "\n0100 .... = Version: 4\n\n\n.... 0101 = Header Length: 20 bytes (5)\n\n\nDifferentiated Services Field: 0x00 (DSCP: CS0, ECN: Not-ECT)\n\n\n0000 00.. = Differentiated Services Codepoint: Default (0)\n\n\n.... ..00 = Explicit Congestion Notification: Not ECN-Capable Transport (0)\n\n\nTotal Length: 64\n\n\nIdentification: 0xe2d3 (58067)\n\n\nFlags: 0x40, Don't fragment\n\n\n0... .... = Reserved bit: Not set\n\n\n.1.. .... = Don't fragment: Set\n\n\n..0. .... = More fragments: Not set\n\n\nFragment Offset: 0\n\n\nTime to Live: 128\n\n\nProtocol: TCP (6)\n\n\nHeader Checksum: 0xf439 [validation disabled]\n\n\nHeader checksum status: Unverified\n\n\nSource Address: 192.168.1.147\n\n\nDestination Address: 81.192.15.175\n\n\n",
            "Layer TCP": "\nSource Port: 64372\n\n\nDestination Port: 443\n\n\nStream index: 0\n\n\nTCP Segment Len: 24\n\n\nSequence Number: 2220    (relative sequence number)\n\n\nSequence Number (raw): 3437900268\n\n\nNext Sequence Number: 2244    (relative sequence number)\n\n\nAcknowledgment Number: 1    (relative ack number)\n\n\nAcknowledgment number (raw): 3848498196\n\n\n0101 .... = Header Length: 20 bytes (5)\n\n\nFlags: 0x018 (PSH, ACK)\n\n\n000. .... .... = Reserved: Not set\n\n\n...0 .... .... = Nonce: Not set\n\n\n.... 0... .... = Congestion Window Reduced (CWR): Not set\n\n\n.... .0.. .... = ECN-Echo: Not set\n\n\n.... ..0. .... = Urgent: Not set\n\n\n.... ...1 .... = Acknowledgment: Set\n\n\n.... .... 1... = Push: Set\n\n\n.... .... .0.. = Reset: Not set\n\n\n.... .... ..0. = Syn: Not set\n\n\n.... .... ...0 = Fin: Not set\n\n\nTCP Flags: \u00b7\u00b7\u00b7\u00b7\u00b7\u00b7\u00b7AP\u00b7\u00b7\u00b7\n\n\nWindow: 511\n\n\nCalculated window size: 511\n\n\nWindow size scaling factor: -1 (unknown)\n\n\nChecksum: 0x4ce5 [unverified]\n\n\nChecksum Status: Unverified\n\n\nUrgent Pointer: 0\n\n\nSEQ/ACK analysis\n\n\nBytes in flight: 2243\n\n\nBytes sent since last PSH flag: 24\n\n\nTimestamps\n\n\nTime since first frame in this TCP stream: 0.000212000 seconds\n\n\nTime since previous frame in this TCP stream: 0.000211000 seconds\n\n\nTCP payload (24 bytes)\n\n\n",
            "Layer TLS": "\nTLSv1.2 Record Layer: Application Data Protocol: http-over-tls\n\n\nContent Type: Application Data (23)\n\n\nVersion: TLS 1.2 (0x0303)\n\n\nLength: 19\n\n\nEncrypted Application Data: 9cfb530450d209d6c734017dee42e67436b085\n\n\nApplication Data Protocol: http-over-tls\n\n\n"
        },
        {
            "lenght": "60",
            "Layer ETH": "\nDestination: 44:39:c4:59:3b:02\n\n\nAddress: 44:39:c4:59:3b:02\n\n\n.... ..0. .... .... .... .... = LG bit: Globally unique address (factory default)\n\n\n.... ...0 .... .... .... .... = IG bit: Individual address (unicast)\n\n\nSource: 90:98:38:97:e0:a0\n\n\n.... ..0. .... .... .... .... = LG bit: Globally unique address (factory default)\n\n\n.... ...0 .... .... .... .... = IG bit: Individual address (unicast)\n\n\nType: IPv4 (0x0800)\n\n\nPadding: 000000000000\n\n\nAddress: 90:98:38:97:e0:a0\n\n\n",
            "Layer IP": "\n0100 .... = Version: 4\n\n\n.... 0101 = Header Length: 20 bytes (5)\n\n\nDifferentiated Services Field: 0x00 (DSCP: CS0, ECN: Not-ECT)\n\n\n0000 00.. = Differentiated Services Codepoint: Default (0)\n\n\n.... ..00 = Explicit Congestion Notification: Not ECN-Capable Transport (0)\n\n\nTotal Length: 40\n\n\nIdentification: 0xf4be (62654)\n\n\nFlags: 0x00\n\n\n0... .... = Reserved bit: Not set\n\n\n.0.. .... = Don't fragment: Not set\n\n\n..0. .... = More fragments: Not set\n\n\nFragment Offset: 0\n\n\nTime to Live: 123\n\n\nProtocol: TCP (6)\n\n\nHeader Checksum: 0x2767 [validation disabled]\n\n\nHeader checksum status: Unverified\n\n\nSource Address: 81.192.15.175\n\n\nDestination Address: 192.168.1.147\n\n\n",
            "Layer TCP": "\nSource Port: 443\n\n\nDestination Port: 64372\n\n\nStream index: 0\n\n\nTCP Segment Len: 0\n\n\nSequence Number: 1    (relative sequence number)\n\n\nSequence Number (raw): 3848498196\n\n\nNext Sequence Number: 1    (relative sequence number)\n\n\nAcknowledgment Number: 2220    (relative ack number)\n\n\nAcknowledgment number (raw): 3437900268\n\n\n0101 .... = Header Length: 20 bytes (5)\n\n\nFlags: 0x010 (ACK)\n\n\n000. .... .... = Reserved: Not set\n\n\n...0 .... .... = Nonce: Not set\n\n\n.... 0... .... = Congestion Window Reduced (CWR): Not set\n\n\n.... .0.. .... = ECN-Echo: Not set\n\n\n.... ..0. .... = Urgent: Not set\n\n\n.... ...1 .... = Acknowledgment: Set\n\n\n.... .... 0... = Push: Not set\n\n\n.... .... .0.. = Reset: Not set\n\n\n.... .... ..0. = Syn: Not set\n\n\n.... .... ...0 = Fin: Not set\n\n\nTCP Flags: \u00b7\u00b7\u00b7\u00b7\u00b7\u00b7\u00b7A\u00b7\u00b7\u00b7\u00b7\n\n\nWindow: 322\n\n\nCalculated window size: 322\n\n\nWindow size scaling factor: -1 (unknown)\n\n\nChecksum: 0x3d69 [unverified]\n\n\nChecksum Status: Unverified\n\n\nUrgent Pointer: 0\n\n\nSEQ/ACK analysis\n\n\nThis is an ACK to the segment in frame: 5\n\n\nThe RTT to ACK the segment was: 0.006511000 seconds\n\n\nTimestamps\n\n\nTime since first frame in this TCP stream: 0.006512000 seconds\n\n\nTime since previous frame in this TCP stream: 0.006300000 seconds\n\n\n"
        },
        {
            "lenght": "1466",
            "Layer ETH": "\nDestination: 44:39:c4:59:3b:02\n\n\nAddress: 44:39:c4:59:3b:02\n\n\n.... ..0. .... .... .... .... = LG bit: Globally unique address (factory default)\n\n\n.... ...0 .... .... .... .... = IG bit: Individual address (unicast)\n\n\nSource: 90:98:38:97:e0:a0\n\n\n.... ..0. .... .... .... .... = LG bit: Globally unique address (factory default)\n\n\n.... ...0 .... .... .... .... = IG bit: Individual address (unicast)\n\n\nType: IPv4 (0x0800)\n\n\nAddress: 90:98:38:97:e0:a0\n\n\n",
            "Layer IP": "\n0100 .... = Version: 4\n\n\n.... 0101 = Header Length: 20 bytes (5)\n\n\nDifferentiated Services Field: 0x00 (DSCP: CS0, ECN: Not-ECT)\n\n\n0000 00.. = Differentiated Services Codepoint: Default (0)\n\n\n.... ..00 = Explicit Congestion Notification: Not ECN-Capable Transport (0)\n\n\nTotal Length: 1452\n\n\nIdentification: 0xf4bf (62655)\n\n\nFlags: 0x00\n\n\n0... .... = Reserved bit: Not set\n\n\n.0.. .... = Don't fragment: Not set\n\n\n..0. .... = More fragments: Not set\n\n\nFragment Offset: 0\n\n\nTime to Live: 123\n\n\nProtocol: TCP (6)\n\n\nHeader Checksum: 0x21e2 [validation disabled]\n\n\nHeader checksum status: Unverified\n\n\nSource Address: 81.192.15.175\n\n\nDestination Address: 192.168.1.147\n\n\n",
            "Layer TCP": "\nSource Port: 443\n\n\nDestination Port: 64372\n\n\nStream index: 0\n\n\nTCP Segment Len: 1412\n\n\nSequence Number: 1    (relative sequence number)\n\n\nSequence Number (raw): 3848498196\n\n\nNext Sequence Number: 1413    (relative sequence number)\n\n\nAcknowledgment Number: 2244    (relative ack number)\n\n\nAcknowledgment number (raw): 3437900292\n\n\n0101 .... = Header Length: 20 bytes (5)\n\n\nFlags: 0x010 (ACK)\n\n\n000. .... .... = Reserved: Not set\n\n\n...0 .... .... = Nonce: Not set\n\n\n.... 0... .... = Congestion Window Reduced (CWR): Not set\n\n\n.... .0.. .... = ECN-Echo: Not set\n\n\n.... ..0. .... = Urgent: Not set\n\n\n.... ...1 .... = Acknowledgment: Set\n\n\n.... .... 0... = Push: Not set\n\n\n.... .... .0.. = Reset: Not set\n\n\n.... .... ..0. = Syn: Not set\n\n\n.... .... ...0 = Fin: Not set\n\n\nTCP Flags: \u00b7\u00b7\u00b7\u00b7\u00b7\u00b7\u00b7A\u00b7\u00b7\u00b7\u00b7\n\n\nWindow: 322\n\n\nCalculated window size: 322\n\n\nWindow size scaling factor: -1 (unknown)\n\n\nChecksum: 0x131a [unverified]\n\n\nChecksum Status: Unverified\n\n\nUrgent Pointer: 0\n\n\nSEQ/ACK analysis\n\n\nThis is an ACK to the segment in frame: 6\n\n\nThe RTT to ACK the segment was: 0.006862000 seconds\n\n\nBytes in flight: 1412\n\n\nBytes sent since last PSH flag: 1412\n\n\nTimestamps\n\n\nTime since first frame in this TCP stream: 0.007074000 seconds\n\n\nTime since previous frame in this TCP stream: 0.000562000 seconds\n\n\nTCP payload (1412 bytes)\n\n\nTCP segment data (299 bytes)\n\n\n",
            "Layer TLS": "\nTLSv1.2 Record Layer: Application Data Protocol: http-over-tls\n\n\nContent Type: Application Data (23)\n\n\nVersion: TLS 1.2 (0x0303)\n\n\nLength: 1108\n\n\nEncrypted Application Data: 7e74bbba8542fcba6969d4aac28254201ba70d1e1dca35c73ec562445cf8531ad00942be\u2026\n\n\nApplication Data Protocol: http-over-tls\n\n\n"
        },
        {
            "lenght": "1056",
            "Layer ETH": "\nDestination: 44:39:c4:59:3b:02\n\n\nAddress: 44:39:c4:59:3b:02\n\n\n.... ..0. .... .... .... .... = LG bit: Globally unique address (factory default)\n\n\n.... ...0 .... .... .... .... = IG bit: Individual address (unicast)\n\n\nSource: 90:98:38:97:e0:a0\n\n\n.... ..0. .... .... .... .... = LG bit: Globally unique address (factory default)\n\n\n.... ...0 .... .... .... .... = IG bit: Individual address (unicast)\n\n\nType: IPv4 (0x0800)\n\n\nAddress: 90:98:38:97:e0:a0\n\n\n",
            "Layer IP": "\n0100 .... = Version: 4\n\n\n.... 0101 = Header Length: 20 bytes (5)\n\n\nDifferentiated Services Field: 0x00 (DSCP: CS0, ECN: Not-ECT)\n\n\n0000 00.. = Differentiated Services Codepoint: Default (0)\n\n\n.... ..00 = Explicit Congestion Notification: Not ECN-Capable Transport (0)\n\n\nTotal Length: 1042\n\n\nIdentification: 0xf4c0 (62656)\n\n\nFlags: 0x00\n\n\n0... .... = Reserved bit: Not set\n\n\n.0.. .... = Don't fragment: Not set\n\n\n..0. .... = More fragments: Not set\n\n\nFragment Offset: 0\n\n\nTime to Live: 123\n\n\nProtocol: TCP (6)\n\n\nHeader Checksum: 0x237b [validation disabled]\n\n\nHeader checksum status: Unverified\n\n\nSource Address: 81.192.15.175\n\n\nDestination Address: 192.168.1.147\n\n\n",
            "Layer TCP": "\nSource Port: 443\n\n\nDestination Port: 64372\n\n\nStream index: 0\n\n\nTCP Segment Len: 1002\n\n\nSequence Number: 1413    (relative sequence number)\n\n\nSequence Number (raw): 3848499608\n\n\nNext Sequence Number: 2415    (relative sequence number)\n\n\nAcknowledgment Number: 2244    (relative ack number)\n\n\nAcknowledgment number (raw): 3437900292\n\n\n0101 .... = Header Length: 20 bytes (5)\n\n\nFlags: 0x018 (PSH, ACK)\n\n\n000. .... .... = Reserved: Not set\n\n\n...0 .... .... = Nonce: Not set\n\n\n.... 0... .... = Congestion Window Reduced (CWR): Not set\n\n\n.... .0.. .... = ECN-Echo: Not set\n\n\n.... ..0. .... = Urgent: Not set\n\n\n.... ...1 .... = Acknowledgment: Set\n\n\n.... .... 1... = Push: Set\n\n\n.... .... .0.. = Reset: Not set\n\n\n.... .... ..0. = Syn: Not set\n\n\n.... .... ...0 = Fin: Not set\n\n\nTCP Flags: \u00b7\u00b7\u00b7\u00b7\u00b7\u00b7\u00b7AP\u00b7\u00b7\u00b7\n\n\nWindow: 322\n\n\nCalculated window size: 322\n\n\nWindow size scaling factor: -1 (unknown)\n\n\nChecksum: 0xeade [unverified]\n\n\nChecksum Status: Unverified\n\n\nUrgent Pointer: 0\n\n\nSEQ/ACK analysis\n\n\nBytes in flight: 2414\n\n\nBytes sent since last PSH flag: 2414\n\n\nTimestamps\n\n\nTime since first frame in this TCP stream: 0.007075000 seconds\n\n\nTime since previous frame in this TCP stream: 0.000001000 seconds\n\n\nTCP payload (1002 bytes)\n\n\nTCP segment data (859 bytes)\n\n\nDATALayer TLS:\n\n\nTLSv1.2 Record Layer: Application Data Protocol: http-over-tls\n\n\nContent Type: Application Data (23)\n\n\nVersion: TLS 1.2 (0x0303)\n\n\nLength: 1153\n\n\nEncrypted Application Data: aaae4a21716b40729a422551bc92b67b62ee202b07612edb2786ab9b225c8d2e90085f68\u2026\n\n\nApplication Data Protocol: http-over-tls\n\n\n",
            "Layer TLS": "\nTLSv1.2 Record Layer: Application Data Protocol: http-over-tls\n\n\nContent Type: Application Data (23)\n\n\nVersion: TLS 1.2 (0x0303)\n\n\nLength: 138\n\n\nEncrypted Application Data: b38371208f5b69ef0d742f2ebcd411def459712a26d3fba4ce1dd82801ed3894933ab483\u2026\n\n\nApplication Data Protocol: http-over-tls\n\n\n"
        },
        {
            "lenght": "54",
            "Layer ETH": "\nDestination: 90:98:38:97:e0:a0\n\n\nAddress: 90:98:38:97:e0:a0\n\n\n.... ..0. .... .... .... .... = LG bit: Globally unique address (factory default)\n\n\n.... ...0 .... .... .... .... = IG bit: Individual address (unicast)\n\n\nSource: 44:39:c4:59:3b:02\n\n\n.... ..0. .... .... .... .... = LG bit: Globally unique address (factory default)\n\n\n.... ...0 .... .... .... .... = IG bit: Individual address (unicast)\n\n\nType: IPv4 (0x0800)\n\n\nAddress: 44:39:c4:59:3b:02\n\n\n",
            "Layer IP": "\n0100 .... = Version: 4\n\n\n.... 0101 = Header Length: 20 bytes (5)\n\n\nDifferentiated Services Field: 0x00 (DSCP: CS0, ECN: Not-ECT)\n\n\n0000 00.. = Differentiated Services Codepoint: Default (0)\n\n\n.... ..00 = Explicit Congestion Notification: Not ECN-Capable Transport (0)\n\n\nTotal Length: 40\n\n\nIdentification: 0xe2d4 (58068)\n\n\nFlags: 0x40, Don't fragment\n\n\n0... .... = Reserved bit: Not set\n\n\n.1.. .... = Don't fragment: Set\n\n\n..0. .... = More fragments: Not set\n\n\nFragment Offset: 0\n\n\nTime to Live: 128\n\n\nProtocol: TCP (6)\n\n\nHeader Checksum: 0xf450 [validation disabled]\n\n\nHeader checksum status: Unverified\n\n\nSource Address: 192.168.1.147\n\n\nDestination Address: 81.192.15.175\n\n\n",
            "Layer TCP": "\nSource Port: 64372\n\n\nDestination Port: 443\n\n\nStream index: 0\n\n\nTCP Segment Len: 0\n\n\nSequence Number: 2244    (relative sequence number)\n\n\nSequence Number (raw): 3437900292\n\n\nNext Sequence Number: 2244    (relative sequence number)\n\n\nAcknowledgment Number: 2415    (relative ack number)\n\n\nAcknowledgment number (raw): 3848500610\n\n\n0101 .... = Header Length: 20 bytes (5)\n\n\nFlags: 0x010 (ACK)\n\n\n000. .... .... = Reserved: Not set\n\n\n...0 .... .... = Nonce: Not set\n\n\n.... 0... .... = Congestion Window Reduced (CWR): Not set\n\n\n.... .0.. .... = ECN-Echo: Not set\n\n\n.... ..0. .... = Urgent: Not set\n\n\n.... ...1 .... = Acknowledgment: Set\n\n\n.... .... 0... = Push: Not set\n\n\n.... .... .0.. = Reset: Not set\n\n\n.... .... ..0. = Syn: Not set\n\n\n.... .... ...0 = Fin: Not set\n\n\nTCP Flags: \u00b7\u00b7\u00b7\u00b7\u00b7\u00b7\u00b7A\u00b7\u00b7\u00b7\u00b7\n\n\nWindow: 512\n\n\nCalculated window size: 512\n\n\nWindow size scaling factor: -1 (unknown)\n\n\nChecksum: 0x3325 [unverified]\n\n\nChecksum Status: Unverified\n\n\nUrgent Pointer: 0\n\n\nSEQ/ACK analysis\n\n\nThis is an ACK to the segment in frame: 9\n\n\nThe RTT to ACK the segment was: 0.000084000 seconds\n\n\nTimestamps\n\n\nTime since first frame in this TCP stream: 0.007159000 seconds\n\n\nTime since previous frame in this TCP stream: 0.000084000 seconds\n\n\n"
        },
        {
            "lenght": "1462",
            "Layer ETH": "\nDestination: 90:98:38:97:e0:a0\n\n\nAddress: 90:98:38:97:e0:a0\n\n\n.... ..0. .... .... .... .... = LG bit: Globally unique address (factory default)\n\n\n.... ...0 .... .... .... .... = IG bit: Individual address (unicast)\n\n\nSource: 44:39:c4:59:3b:02\n\n\n.... ..0. .... .... .... .... = LG bit: Globally unique address (factory default)\n\n\n.... ...0 .... .... .... .... = IG bit: Individual address (unicast)\n\n\nType: IPv4 (0x0800)\n\n\nAddress: 44:39:c4:59:3b:02\n\n\n",
            "Layer IP": "\n0100 .... = Version: 4\n\n\n.... 0101 = Header Length: 20 bytes (5)\n\n\nDifferentiated Services Field: 0x00 (DSCP: CS0, ECN: Not-ECT)\n\n\n0000 00.. = Differentiated Services Codepoint: Default (0)\n\n\n.... ..00 = Explicit Congestion Notification: Not ECN-Capable Transport (0)\n\n\nTotal Length: 1448\n\n\nIdentification: 0xe97e (59774)\n\n\nFlags: 0x40, Don't fragment\n\n\n0... .... = Reserved bit: Not set\n\n\n.1.. .... = Don't fragment: Set\n\n\n..0. .... = More fragments: Not set\n\n\nFragment Offset: 0\n\n\nTime to Live: 128\n\n\nProtocol: TCP (6)\n\n\nHeader Checksum: 0xfaae [validation disabled]\n\n\nHeader checksum status: Unverified\n\n\nSource Address: 192.168.1.147\n\n\nDestination Address: 74.125.4.106\n\n\n",
            "Layer TCP": "\nSource Port: 64378\n\n\nDestination Port: 443\n\n\nStream index: 1\n\n\nTCP Segment Len: 1408\n\n\nSequence Number: 1    (relative sequence number)\n\n\nSequence Number (raw): 1726350411\n\n\nNext Sequence Number: 1409    (relative sequence number)\n\n\nAcknowledgment Number: 1    (relative ack number)\n\n\nAcknowledgment number (raw): 3692199701\n\n\n0101 .... = Header Length: 20 bytes (5)\n\n\nFlags: 0x010 (ACK)\n\n\n000. .... .... = Reserved: Not set\n\n\n...0 .... .... = Nonce: Not set\n\n\n.... 0... .... = Congestion Window Reduced (CWR): Not set\n\n\n.... .0.. .... = ECN-Echo: Not set\n\n\n.... ..0. .... = Urgent: Not set\n\n\n.... ...1 .... = Acknowledgment: Set\n\n\n.... .... 0... = Push: Not set\n\n\n.... .... .0.. = Reset: Not set\n\n\n.... .... ..0. = Syn: Not set\n\n\n.... .... ...0 = Fin: Not set\n\n\nTCP Flags: \u00b7\u00b7\u00b7\u00b7\u00b7\u00b7\u00b7A\u00b7\u00b7\u00b7\u00b7\n\n\nWindow: 517\n\n\nCalculated window size: 517\n\n\nWindow size scaling factor: -1 (unknown)\n\n\nChecksum: 0xb5b7 [unverified]\n\n\nChecksum Status: Unverified\n\n\nUrgent Pointer: 0\n\n\nSEQ/ACK analysis\n\n\nBytes in flight: 1408\n\n\nBytes sent since last PSH flag: 1408\n\n\nTimestamps\n\n\nTime since first frame in this TCP stream: 0.000000000 seconds\n\n\nTime since previous frame in this TCP stream: 0.000000000 seconds\n\n\nTCP payload (1408 bytes)\n\n\nTCP segment data (1408 bytes)\n\n\n",
            "Layer TLS": "\n"
        },
        {
            "lenght": "854",
            "Layer ETH": "\nDestination: 90:98:38:97:e0:a0\n\n\nAddress: 90:98:38:97:e0:a0\n\n\n.... ..0. .... .... .... .... = LG bit: Globally unique address (factory default)\n\n\n.... ...0 .... .... .... .... = IG bit: Individual address (unicast)\n\n\nSource: 44:39:c4:59:3b:02\n\n\n.... ..0. .... .... .... .... = LG bit: Globally unique address (factory default)\n\n\n.... ...0 .... .... .... .... = IG bit: Individual address (unicast)\n\n\nType: IPv4 (0x0800)\n\n\nAddress: 44:39:c4:59:3b:02\n\n\n",
            "Layer IP": "\n0100 .... = Version: 4\n\n\n.... 0101 = Header Length: 20 bytes (5)\n\n\nDifferentiated Services Field: 0x00 (DSCP: CS0, ECN: Not-ECT)\n\n\n0000 00.. = Differentiated Services Codepoint: Default (0)\n\n\n.... ..00 = Explicit Congestion Notification: Not ECN-Capable Transport (0)\n\n\nTotal Length: 840\n\n\nIdentification: 0xe97f (59775)\n\n\nFlags: 0x40, Don't fragment\n\n\n0... .... = Reserved bit: Not set\n\n\n.1.. .... = Don't fragment: Set\n\n\n..0. .... = More fragments: Not set\n\n\nFragment Offset: 0\n\n\nTime to Live: 128\n\n\nProtocol: TCP (6)\n\n\nHeader Checksum: 0xfd0d [validation disabled]\n\n\nHeader checksum status: Unverified\n\n\nSource Address: 192.168.1.147\n\n\nDestination Address: 74.125.4.106\n\n\n",
            "Layer TCP": "\nSource Port: 64378\n\n\nDestination Port: 443\n\n\nStream index: 1\n\n\nTCP Segment Len: 800\n\n\nSequence Number: 1409    (relative sequence number)\n\n\nSequence Number (raw): 1726351819\n\n\nNext Sequence Number: 2209    (relative sequence number)\n\n\nAcknowledgment Number: 1    (relative ack number)\n\n\nAcknowledgment number (raw): 3692199701\n\n\n0101 .... = Header Length: 20 bytes (5)\n\n\nFlags: 0x018 (PSH, ACK)\n\n\n000. .... .... = Reserved: Not set\n\n\n...0 .... .... = Nonce: Not set\n\n\n.... 0... .... = Congestion Window Reduced (CWR): Not set\n\n\n.... .0.. .... = ECN-Echo: Not set\n\n\n.... ..0. .... = Urgent: Not set\n\n\n.... ...1 .... = Acknowledgment: Set\n\n\n.... .... 1... = Push: Set\n\n\n.... .... .0.. = Reset: Not set\n\n\n.... .... ..0. = Syn: Not set\n\n\n.... .... ...0 = Fin: Not set\n\n\nTCP Flags: \u00b7\u00b7\u00b7\u00b7\u00b7\u00b7\u00b7AP\u00b7\u00b7\u00b7\n\n\nWindow: 517\n\n\nCalculated window size: 517\n\n\nWindow size scaling factor: -1 (unknown)\n\n\nChecksum: 0x0c57 [unverified]\n\n\nChecksum Status: Unverified\n\n\nUrgent Pointer: 0\n\n\nSEQ/ACK analysis\n\n\nBytes in flight: 2208\n\n\nBytes sent since last PSH flag: 2208\n\n\nTimestamps\n\n\nTime since first frame in this TCP stream: 0.000002000 seconds\n\n\nTime since previous frame in this TCP stream: 0.000002000 seconds\n\n\nTCP payload (800 bytes)\n\n\nTCP segment data (800 bytes)\n\n\nDATALayer TLS:\n\n\nTLSv1.2 Record Layer: Application Data Protocol: http-over-tls\n\n\nContent Type: Application Data (23)\n\n\nVersion: TLS 1.2 (0x0303)\n\n\nLength: 2203\n\n\nEncrypted Application Data: 61bbab19f284eb972f1fc8a9717059d2b9cc16600aceb0c95e3c8eb3c4dae2802f86d1b8\u2026\n\n\nApplication Data Protocol: http-over-tls\n\n\n"
        },
        {
            "lenght": "78",
            "Layer ETH": "\nDestination: 90:98:38:97:e0:a0\n\n\nAddress: 90:98:38:97:e0:a0\n\n\n.... ..0. .... .... .... .... = LG bit: Globally unique address (factory default)\n\n\n.... ...0 .... .... .... .... = IG bit: Individual address (unicast)\n\n\nSource: 44:39:c4:59:3b:02\n\n\n.... ..0. .... .... .... .... = LG bit: Globally unique address (factory default)\n\n\n.... ...0 .... .... .... .... = IG bit: Individual address (unicast)\n\n\nType: IPv4 (0x0800)\n\n\nAddress: 44:39:c4:59:3b:02\n\n\n",
            "Layer IP": "\n0100 .... = Version: 4\n\n\n.... 0101 = Header Length: 20 bytes (5)\n\n\nDifferentiated Services Field: 0x00 (DSCP: CS0, ECN: Not-ECT)\n\n\n0000 00.. = Differentiated Services Codepoint: Default (0)\n\n\n.... ..00 = Explicit Congestion Notification: Not ECN-Capable Transport (0)\n\n\nTotal Length: 64\n\n\nIdentification: 0xe980 (59776)\n\n\nFlags: 0x40, Don't fragment\n\n\n0... .... = Reserved bit: Not set\n\n\n.1.. .... = Don't fragment: Set\n\n\n..0. .... = More fragments: Not set\n\n\nFragment Offset: 0\n\n\nTime to Live: 128\n\n\nProtocol: TCP (6)\n\n\nHeader Checksum: 0x0015 [validation disabled]\n\n\nHeader checksum status: Unverified\n\n\nSource Address: 192.168.1.147\n\n\nDestination Address: 74.125.4.106\n\n\n",
            "Layer TCP": "\nSource Port: 64378\n\n\nDestination Port: 443\n\n\nStream index: 1\n\n\nTCP Segment Len: 24\n\n\nSequence Number: 2209    (relative sequence number)\n\n\nSequence Number (raw): 1726352619\n\n\nNext Sequence Number: 2233    (relative sequence number)\n\n\nAcknowledgment Number: 1    (relative ack number)\n\n\nAcknowledgment number (raw): 3692199701\n\n\n0101 .... = Header Length: 20 bytes (5)\n\n\nFlags: 0x018 (PSH, ACK)\n\n\n000. .... .... = Reserved: Not set\n\n\n...0 .... .... = Nonce: Not set\n\n\n.... 0... .... = Congestion Window Reduced (CWR): Not set\n\n\n.... .0.. .... = ECN-Echo: Not set\n\n\n.... ..0. .... = Urgent: Not set\n\n\n.... ...1 .... = Acknowledgment: Set\n\n\n.... .... 1... = Push: Set\n\n\n.... .... .0.. = Reset: Not set\n\n\n.... .... ..0. = Syn: Not set\n\n\n.... .... ...0 = Fin: Not set\n\n\nTCP Flags: \u00b7\u00b7\u00b7\u00b7\u00b7\u00b7\u00b7AP\u00b7\u00b7\u00b7\n\n\nWindow: 517\n\n\nCalculated window size: 517\n\n\nWindow size scaling factor: -1 (unknown)\n\n\nChecksum: 0x00b0 [unverified]\n\n\nChecksum Status: Unverified\n\n\nUrgent Pointer: 0\n\n\nSEQ/ACK analysis\n\n\nBytes in flight: 2232\n\n\nBytes sent since last PSH flag: 24\n\n\nTimestamps\n\n\nTime since first frame in this TCP stream: 0.000199000 seconds\n\n\nTime since previous frame in this TCP stream: 0.000197000 seconds\n\n\nTCP payload (24 bytes)\n\n\n",
            "Layer TLS": "\nTLSv1.2 Record Layer: Application Data Protocol: http-over-tls\n\n\nContent Type: Application Data (23)\n\n\nVersion: TLS 1.2 (0x0303)\n\n\nLength: 19\n\n\nEncrypted Application Data: 5cbe5d3671e1c5f97b64c0adab1790c412e42e\n\n\nApplication Data Protocol: http-over-tls\n\n\n"
        },
        {
            "lenght": "60",
            "Layer ETH": "\nDestination: 44:39:c4:59:3b:02\n\n\nAddress: 44:39:c4:59:3b:02\n\n\n.... ..0. .... .... .... .... = LG bit: Globally unique address (factory default)\n\n\n.... ...0 .... .... .... .... = IG bit: Individual address (unicast)\n\n\nSource: 90:98:38:97:e0:a0\n\n\n.... ..0. .... .... .... .... = LG bit: Globally unique address (factory default)\n\n\n.... ...0 .... .... .... .... = IG bit: Individual address (unicast)\n\n\nType: IPv4 (0x0800)\n\n\nPadding: 000000000000\n\n\nAddress: 90:98:38:97:e0:a0\n\n\n",
            "Layer IP": "\n0100 .... = Version: 4\n\n\n.... 0101 = Header Length: 20 bytes (5)\n\n\nDifferentiated Services Field: 0x00 (DSCP: CS0, ECN: Not-ECT)\n\n\n0000 00.. = Differentiated Services Codepoint: Default (0)\n\n\n.... ..00 = Explicit Congestion Notification: Not ECN-Capable Transport (0)\n\n\nTotal Length: 40\n\n\nIdentification: 0x258d (9613)\n\n\nFlags: 0x00\n\n\n0... .... = Reserved bit: Not set\n\n\n.0.. .... = Don't fragment: Not set\n\n\n..0. .... = More fragments: Not set\n\n\nFragment Offset: 0\n\n\nTime to Live: 57\n\n\nProtocol: TCP (6)\n\n\nHeader Checksum: 0x4b21 [validation disabled]\n\n\nHeader checksum status: Unverified\n\n\nSource Address: 74.125.4.106\n\n\nDestination Address: 192.168.1.147\n\n\n",
            "Layer TCP": "\nSource Port: 443\n\n\nDestination Port: 64378\n\n\nStream index: 1\n\n\nTCP Segment Len: 0\n\n\nSequence Number: 1    (relative sequence number)\n\n\nSequence Number (raw): 3692199701\n\n\nNext Sequence Number: 1    (relative sequence number)\n\n\nAcknowledgment Number: 1409    (relative ack number)\n\n\nAcknowledgment number (raw): 1726351819\n\n\n0101 .... = Header Length: 20 bytes (5)\n\n\nFlags: 0x010 (ACK)\n\n\n000. .... .... = Reserved: Not set\n\n\n...0 .... .... = Nonce: Not set\n\n\n.... 0... .... = Congestion Window Reduced (CWR): Not set\n\n\n.... .0.. .... = ECN-Echo: Not set\n\n\n.... ..0. .... = Urgent: Not set\n\n\n.... ...1 .... = Acknowledgment: Set\n\n\n.... .... 0... = Push: Not set\n\n\n.... .... .0.. = Reset: Not set\n\n\n.... .... ..0. = Syn: Not set\n\n\n.... .... ...0 = Fin: Not set\n\n\nTCP Flags: \u00b7\u00b7\u00b7\u00b7\u00b7\u00b7\u00b7A\u00b7\u00b7\u00b7\u00b7\n\n\nWindow: 294\n\n\nCalculated window size: 294\n\n\nWindow size scaling factor: -1 (unknown)\n\n\nChecksum: 0xd47c [unverified]\n\n\nChecksum Status: Unverified\n\n\nUrgent Pointer: 0\n\n\nSEQ/ACK analysis\n\n\nThis is an ACK to the segment in frame: 11\n\n\nThe RTT to ACK the segment was: 0.040845000 seconds\n\n\nTimestamps\n\n\nTime since first frame in this TCP stream: 0.040845000 seconds\n\n\nTime since previous frame in this TCP stream: 0.040646000 seconds\n\n\n"
        },
        {
            "lenght": "60",
            "Layer ETH": "\nDestination: 44:39:c4:59:3b:02\n\n\nAddress: 44:39:c4:59:3b:02\n\n\n.... ..0. .... .... .... .... = LG bit: Globally unique address (factory default)\n\n\n.... ...0 .... .... .... .... = IG bit: Individual address (unicast)\n\n\nSource: 90:98:38:97:e0:a0\n\n\n.... ..0. .... .... .... .... = LG bit: Globally unique address (factory default)\n\n\n.... ...0 .... .... .... .... = IG bit: Individual address (unicast)\n\n\nType: IPv4 (0x0800)\n\n\nPadding: 000000000000\n\n\nAddress: 90:98:38:97:e0:a0\n\n\n",
            "Layer IP": "\n0100 .... = Version: 4\n\n\n.... 0101 = Header Length: 20 bytes (5)\n\n\nDifferentiated Services Field: 0x00 (DSCP: CS0, ECN: Not-ECT)\n\n\n0000 00.. = Differentiated Services Codepoint: Default (0)\n\n\n.... ..00 = Explicit Congestion Notification: Not ECN-Capable Transport (0)\n\n\nTotal Length: 40\n\n\nIdentification: 0x258e (9614)\n\n\nFlags: 0x00\n\n\n0... .... = Reserved bit: Not set\n\n\n.0.. .... = Don't fragment: Not set\n\n\n..0. .... = More fragments: Not set\n\n\nFragment Offset: 0\n\n\nTime to Live: 57\n\n\nProtocol: TCP (6)\n\n\nHeader Checksum: 0x4b20 [validation disabled]\n\n\nHeader checksum status: Unverified\n\n\nSource Address: 74.125.4.106\n\n\nDestination Address: 192.168.1.147\n\n\n",
            "Layer TCP": "\nSource Port: 443\n\n\nDestination Port: 64378\n\n\nStream index: 1\n\n\nTCP Segment Len: 0\n\n\nSequence Number: 1    (relative sequence number)\n\n\nSequence Number (raw): 3692199701\n\n\nNext Sequence Number: 1    (relative sequence number)\n\n\nAcknowledgment Number: 2209    (relative ack number)\n\n\nAcknowledgment number (raw): 1726352619\n\n\n0101 .... = Header Length: 20 bytes (5)\n\n\nFlags: 0x010 (ACK)\n\n\n000. .... .... = Reserved: Not set\n\n\n...0 .... .... = Nonce: Not set\n\n\n.... 0... .... = Congestion Window Reduced (CWR): Not set\n\n\n.... .0.. .... = ECN-Echo: Not set\n\n\n.... ..0. .... = Urgent: Not set\n\n\n.... ...1 .... = Acknowledgment: Set\n\n\n.... .... 0... = Push: Not set\n\n\n.... .... .0.. = Reset: Not set\n\n\n.... .... ..0. = Syn: Not set\n\n\n.... .... ...0 = Fin: Not set\n\n\nTCP Flags: \u00b7\u00b7\u00b7\u00b7\u00b7\u00b7\u00b7A\u00b7\u00b7\u00b7\u00b7\n\n\nWindow: 305\n\n\nCalculated window size: 305\n\n\nWindow size scaling factor: -1 (unknown)\n\n\nChecksum: 0xd151 [unverified]\n\n\nChecksum Status: Unverified\n\n\nUrgent Pointer: 0\n\n\nSEQ/ACK analysis\n\n\nThis is an ACK to the segment in frame: 12\n\n\nThe RTT to ACK the segment was: 0.049797000 seconds\n\n\nTimestamps\n\n\nTime since first frame in this TCP stream: 0.049799000 seconds\n\n\nTime since previous frame in this TCP stream: 0.008954000 seconds\n\n\n"
        },
        {
            "lenght": "60",
            "Layer ETH": "\nDestination: 44:39:c4:59:3b:02\n\n\nAddress: 44:39:c4:59:3b:02\n\n\n.... ..0. .... .... .... .... = LG bit: Globally unique address (factory default)\n\n\n.... ...0 .... .... .... .... = IG bit: Individual address (unicast)\n\n\nSource: 90:98:38:97:e0:a0\n\n\n.... ..0. .... .... .... .... = LG bit: Globally unique address (factory default)\n\n\n.... ...0 .... .... .... .... = IG bit: Individual address (unicast)\n\n\nType: IPv4 (0x0800)\n\n\nPadding: 000000000000\n\n\nAddress: 90:98:38:97:e0:a0\n\n\n",
            "Layer IP": "\n0100 .... = Version: 4\n\n\n.... 0101 = Header Length: 20 bytes (5)\n\n\nDifferentiated Services Field: 0x00 (DSCP: CS0, ECN: Not-ECT)\n\n\n0000 00.. = Differentiated Services Codepoint: Default (0)\n\n\n.... ..00 = Explicit Congestion Notification: Not ECN-Capable Transport (0)\n\n\nTotal Length: 40\n\n\nIdentification: 0x258f (9615)\n\n\nFlags: 0x00\n\n\n0... .... = Reserved bit: Not set\n\n\n.0.. .... = Don't fragment: Not set\n\n\n..0. .... = More fragments: Not set\n\n\nFragment Offset: 0\n\n\nTime to Live: 57\n\n\nProtocol: TCP (6)\n\n\nHeader Checksum: 0x4b1f [validation disabled]\n\n\nHeader checksum status: Unverified\n\n\nSource Address: 74.125.4.106\n\n\nDestination Address: 192.168.1.147\n\n\n",
            "Layer TCP": "\nSource Port: 443\n\n\nDestination Port: 64378\n\n\nStream index: 1\n\n\nTCP Segment Len: 0\n\n\nSequence Number: 1    (relative sequence number)\n\n\nSequence Number (raw): 3692199701\n\n\nNext Sequence Number: 1    (relative sequence number)\n\n\nAcknowledgment Number: 2233    (relative ack number)\n\n\nAcknowledgment number (raw): 1726352643\n\n\n0101 .... = Header Length: 20 bytes (5)\n\n\nFlags: 0x010 (ACK)\n\n\n000. .... .... = Reserved: Not set\n\n\n...0 .... .... = Nonce: Not set\n\n\n.... 0... .... = Congestion Window Reduced (CWR): Not set\n\n\n.... .0.. .... = ECN-Echo: Not set\n\n\n.... ..0. .... = Urgent: Not set\n\n\n.... ...1 .... = Acknowledgment: Set\n\n\n.... .... 0... = Push: Not set\n\n\n.... .... .0.. = Reset: Not set\n\n\n.... .... ..0. = Syn: Not set\n\n\n.... .... ...0 = Fin: Not set\n\n\nTCP Flags: \u00b7\u00b7\u00b7\u00b7\u00b7\u00b7\u00b7A\u00b7\u00b7\u00b7\u00b7\n\n\nWindow: 305\n\n\nCalculated window size: 305\n\n\nWindow size scaling factor: -1 (unknown)\n\n\nChecksum: 0xd139 [unverified]\n\n\nChecksum Status: Unverified\n\n\nUrgent Pointer: 0\n\n\nSEQ/ACK analysis\n\n\nThis is an ACK to the segment in frame: 13\n\n\nThe RTT to ACK the segment was: 0.049600000 seconds\n\n\nTimestamps\n\n\nTime since first frame in this TCP stream: 0.049799000 seconds\n\n\nTime since previous frame in this TCP stream: 0.000000000 seconds\n\n\n"
        },
        {
            "lenght": "1462",
            "Layer ETH": "\nDestination: 44:39:c4:59:3b:02\n\n\nAddress: 44:39:c4:59:3b:02\n\n\n.... ..0. .... .... .... .... = LG bit: Globally unique address (factory default)\n\n\n.... ...0 .... .... .... .... = IG bit: Individual address (unicast)\n\n\nSource: 90:98:38:97:e0:a0\n\n\n.... ..0. .... .... .... .... = LG bit: Globally unique address (factory default)\n\n\n.... ...0 .... .... .... .... = IG bit: Individual address (unicast)\n\n\nType: IPv4 (0x0800)\n\n\nAddress: 90:98:38:97:e0:a0\n\n\n",
            "Layer IP": "\n0100 .... = Version: 4\n\n\n.... 0101 = Header Length: 20 bytes (5)\n\n\nDifferentiated Services Field: 0x00 (DSCP: CS0, ECN: Not-ECT)\n\n\n0000 00.. = Differentiated Services Codepoint: Default (0)\n\n\n.... ..00 = Explicit Congestion Notification: Not ECN-Capable Transport (0)\n\n\nTotal Length: 1448\n\n\nIdentification: 0x2590 (9616)\n\n\nFlags: 0x00\n\n\n0... .... = Reserved bit: Not set\n\n\n.0.. .... = Don't fragment: Not set\n\n\n..0. .... = More fragments: Not set\n\n\nFragment Offset: 0\n\n\nTime to Live: 57\n\n\nProtocol: TCP (6)\n\n\nHeader Checksum: 0x459e [validation disabled]\n\n\nHeader checksum status: Unverified\n\n\nSource Address: 74.125.4.106\n\n\nDestination Address: 192.168.1.147\n\n\n",
            "Layer TCP": "\nSource Port: 443\n\n\nDestination Port: 64378\n\n\nStream index: 1\n\n\nTCP Segment Len: 1408\n\n\nSequence Number: 1    (relative sequence number)\n\n\nSequence Number (raw): 3692199701\n\n\nNext Sequence Number: 1409    (relative sequence number)\n\n\nAcknowledgment Number: 2233    (relative ack number)\n\n\nAcknowledgment number (raw): 1726352643\n\n\n0101 .... = Header Length: 20 bytes (5)\n\n\nFlags: 0x010 (ACK)\n\n\n000. .... .... = Reserved: Not set\n\n\n...0 .... .... = Nonce: Not set\n\n\n.... 0... .... = Congestion Window Reduced (CWR): Not set\n\n\n.... .0.. .... = ECN-Echo: Not set\n\n\n.... ..0. .... = Urgent: Not set\n\n\n.... ...1 .... = Acknowledgment: Set\n\n\n.... .... 0... = Push: Not set\n\n\n.... .... .0.. = Reset: Not set\n\n\n.... .... ..0. = Syn: Not set\n\n\n.... .... ...0 = Fin: Not set\n\n\nTCP Flags: \u00b7\u00b7\u00b7\u00b7\u00b7\u00b7\u00b7A\u00b7\u00b7\u00b7\u00b7\n\n\nWindow: 305\n\n\nCalculated window size: 305\n\n\nWindow size scaling factor: -1 (unknown)\n\n\nChecksum: 0x14af [unverified]\n\n\nChecksum Status: Unverified\n\n\nUrgent Pointer: 0\n\n\nSEQ/ACK analysis\n\n\nBytes in flight: 1408\n\n\nBytes sent since last PSH flag: 1408\n\n\nTimestamps\n\n\nTime since first frame in this TCP stream: 0.053476000 seconds\n\n\nTime since previous frame in this TCP stream: 0.003677000 seconds\n\n\nTCP payload (1408 bytes)\n\n\nTCP segment data (294 bytes)\n\n\n",
            "Layer TLS": "\nTLSv1.2 Record Layer: Application Data Protocol: http-over-tls\n\n\nContent Type: Application Data (23)\n\n\nVersion: TLS 1.2 (0x0303)\n\n\nLength: 1109\n\n\nEncrypted Application Data: 594a92dd56bc566c48f083536a36a2961e084d700d4da6d7f8b71c6c1b4a2e14863e108c\u2026\n\n\nApplication Data Protocol: http-over-tls\n\n\n"
        },
        {
            "lenght": "1462",
            "Layer ETH": "\nDestination: 44:39:c4:59:3b:02\n\n\nAddress: 44:39:c4:59:3b:02\n\n\n.... ..0. .... .... .... .... = LG bit: Globally unique address (factory default)\n\n\n.... ...0 .... .... .... .... = IG bit: Individual address (unicast)\n\n\nSource: 90:98:38:97:e0:a0\n\n\n.... ..0. .... .... .... .... = LG bit: Globally unique address (factory default)\n\n\n.... ...0 .... .... .... .... = IG bit: Individual address (unicast)\n\n\nType: IPv4 (0x0800)\n\n\nAddress: 90:98:38:97:e0:a0\n\n\n",
            "Layer IP": "\n0100 .... = Version: 4\n\n\n.... 0101 = Header Length: 20 bytes (5)\n\n\nDifferentiated Services Field: 0x00 (DSCP: CS0, ECN: Not-ECT)\n\n\n0000 00.. = Differentiated Services Codepoint: Default (0)\n\n\n.... ..00 = Explicit Congestion Notification: Not ECN-Capable Transport (0)\n\n\nTotal Length: 1448\n\n\nIdentification: 0x2591 (9617)\n\n\nFlags: 0x00\n\n\n0... .... = Reserved bit: Not set\n\n\n.0.. .... = Don't fragment: Not set\n\n\n..0. .... = More fragments: Not set\n\n\nFragment Offset: 0\n\n\nTime to Live: 57\n\n\nProtocol: TCP (6)\n\n\nHeader Checksum: 0x459d [validation disabled]\n\n\nHeader checksum status: Unverified\n\n\nSource Address: 74.125.4.106\n\n\nDestination Address: 192.168.1.147\n\n\n",
            "Layer TCP": "\nSource Port: 443\n\n\nDestination Port: 64378\n\n\nStream index: 1\n\n\nTCP Segment Len: 1408\n\n\nSequence Number: 1409    (relative sequence number)\n\n\nSequence Number (raw): 3692201109\n\n\nNext Sequence Number: 2817    (relative sequence number)\n\n\nAcknowledgment Number: 2233    (relative ack number)\n\n\nAcknowledgment number (raw): 1726352643\n\n\n0101 .... = Header Length: 20 bytes (5)\n\n\nFlags: 0x018 (PSH, ACK)\n\n\n000. .... .... = Reserved: Not set\n\n\n...0 .... .... = Nonce: Not set\n\n\n.... 0... .... = Congestion Window Reduced (CWR): Not set\n\n\n.... .0.. .... = ECN-Echo: Not set\n\n\n.... ..0. .... = Urgent: Not set\n\n\n.... ...1 .... = Acknowledgment: Set\n\n\n.... .... 1... = Push: Set\n\n\n.... .... .0.. = Reset: Not set\n\n\n.... .... ..0. = Syn: Not set\n\n\n.... .... ...0 = Fin: Not set\n\n\nTCP Flags: \u00b7\u00b7\u00b7\u00b7\u00b7\u00b7\u00b7AP\u00b7\u00b7\u00b7\n\n\nWindow: 305\n\n\nCalculated window size: 305\n\n\nWindow size scaling factor: -1 (unknown)\n\n\nChecksum: 0xc41d [unverified]\n\n\nChecksum Status: Unverified\n\n\nUrgent Pointer: 0\n\n\nSEQ/ACK analysis\n\n\nBytes in flight: 2816\n\n\nBytes sent since last PSH flag: 2816\n\n\nTimestamps\n\n\nTime since first frame in this TCP stream: 0.053477000 seconds\n\n\nTime since previous frame in this TCP stream: 0.000001000 seconds\n\n\nTCP payload (1408 bytes)\n\n\nTCP segment data (1408 bytes)\n\n\n"
        },
        {
            "lenght": "1462",
            "Layer ETH": "\nDestination: 44:39:c4:59:3b:02\n\n\nAddress: 44:39:c4:59:3b:02\n\n\n.... ..0. .... .... .... .... = LG bit: Globally unique address (factory default)\n\n\n.... ...0 .... .... .... .... = IG bit: Individual address (unicast)\n\n\nSource: 90:98:38:97:e0:a0\n\n\n.... ..0. .... .... .... .... = LG bit: Globally unique address (factory default)\n\n\n.... ...0 .... .... .... .... = IG bit: Individual address (unicast)\n\n\nType: IPv4 (0x0800)\n\n\nAddress: 90:98:38:97:e0:a0\n\n\n",
            "Layer IP": "\n0100 .... = Version: 4\n\n\n.... 0101 = Header Length: 20 bytes (5)\n\n\nDifferentiated Services Field: 0x00 (DSCP: CS0, ECN: Not-ECT)\n\n\n0000 00.. = Differentiated Services Codepoint: Default (0)\n\n\n.... ..00 = Explicit Congestion Notification: Not ECN-Capable Transport (0)\n\n\nTotal Length: 1448\n\n\nIdentification: 0x2592 (9618)\n\n\nFlags: 0x00\n\n\n0... .... = Reserved bit: Not set\n\n\n.0.. .... = Don't fragment: Not set\n\n\n..0. .... = More fragments: Not set\n\n\nFragment Offset: 0\n\n\nTime to Live: 57\n\n\nProtocol: TCP (6)\n\n\nHeader Checksum: 0x459c [validation disabled]\n\n\nHeader checksum status: Unverified\n\n\nSource Address: 74.125.4.106\n\n\nDestination Address: 192.168.1.147\n\n\n",
            "Layer TCP": "\nSource Port: 443\n\n\nDestination Port: 64378\n\n\nStream index: 1\n\n\nTCP Segment Len: 1408\n\n\nSequence Number: 2817    (relative sequence number)\n\n\nSequence Number (raw): 3692202517\n\n\nNext Sequence Number: 4225    (relative sequence number)\n\n\nAcknowledgment Number: 2233    (relative ack number)\n\n\nAcknowledgment number (raw): 1726352643\n\n\n0101 .... = Header Length: 20 bytes (5)\n\n\nFlags: 0x010 (ACK)\n\n\n000. .... .... = Reserved: Not set\n\n\n...0 .... .... = Nonce: Not set\n\n\n.... 0... .... = Congestion Window Reduced (CWR): Not set\n\n\n.... .0.. .... = ECN-Echo: Not set\n\n\n.... ..0. .... = Urgent: Not set\n\n\n.... ...1 .... = Acknowledgment: Set\n\n\n.... .... 0... = Push: Not set\n\n\n.... .... .0.. = Reset: Not set\n\n\n.... .... ..0. = Syn: Not set\n\n\n.... .... ...0 = Fin: Not set\n\n\nTCP Flags: \u00b7\u00b7\u00b7\u00b7\u00b7\u00b7\u00b7A\u00b7\u00b7\u00b7\u00b7\n\n\nWindow: 305\n\n\nCalculated window size: 305\n\n\nWindow size scaling factor: -1 (unknown)\n\n\nChecksum: 0x012e [unverified]\n\n\nChecksum Status: Unverified\n\n\nUrgent Pointer: 0\n\n\nSEQ/ACK analysis\n\n\nBytes in flight: 4224\n\n\nBytes sent since last PSH flag: 1408\n\n\nTimestamps\n\n\nTime since first frame in this TCP stream: 0.053477000 seconds\n\n\nTime since previous frame in this TCP stream: 0.000000000 seconds\n\n\nTCP payload (1408 bytes)\n\n\nTCP segment data (1408 bytes)\n\n\n"
        },
        {
            "lenght": "1462",
            "Layer ETH": "\nDestination: 44:39:c4:59:3b:02\n\n\nAddress: 44:39:c4:59:3b:02\n\n\n.... ..0. .... .... .... .... = LG bit: Globally unique address (factory default)\n\n\n.... ...0 .... .... .... .... = IG bit: Individual address (unicast)\n\n\nSource: 90:98:38:97:e0:a0\n\n\n.... ..0. .... .... .... .... = LG bit: Globally unique address (factory default)\n\n\n.... ...0 .... .... .... .... = IG bit: Individual address (unicast)\n\n\nType: IPv4 (0x0800)\n\n\nAddress: 90:98:38:97:e0:a0\n\n\n",
            "Layer IP": "\n0100 .... = Version: 4\n\n\n.... 0101 = Header Length: 20 bytes (5)\n\n\nDifferentiated Services Field: 0x00 (DSCP: CS0, ECN: Not-ECT)\n\n\n0000 00.. = Differentiated Services Codepoint: Default (0)\n\n\n.... ..00 = Explicit Congestion Notification: Not ECN-Capable Transport (0)\n\n\nTotal Length: 1448\n\n\nIdentification: 0x2593 (9619)\n\n\nFlags: 0x00\n\n\n0... .... = Reserved bit: Not set\n\n\n.0.. .... = Don't fragment: Not set\n\n\n..0. .... = More fragments: Not set\n\n\nFragment Offset: 0\n\n\nTime to Live: 57\n\n\nProtocol: TCP (6)\n\n\nHeader Checksum: 0x459b [validation disabled]\n\n\nHeader checksum status: Unverified\n\n\nSource Address: 74.125.4.106\n\n\nDestination Address: 192.168.1.147\n\n\n",
            "Layer TCP": "\nSource Port: 443\n\n\nDestination Port: 64378\n\n\nStream index: 1\n\n\nTCP Segment Len: 1408\n\n\nSequence Number: 4225    (relative sequence number)\n\n\nSequence Number (raw): 3692203925\n\n\nNext Sequence Number: 5633    (relative sequence number)\n\n\nAcknowledgment Number: 2233    (relative ack number)\n\n\nAcknowledgment number (raw): 1726352643\n\n\n0101 .... = Header Length: 20 bytes (5)\n\n\nFlags: 0x018 (PSH, ACK)\n\n\n000. .... .... = Reserved: Not set\n\n\n...0 .... .... = Nonce: Not set\n\n\n.... 0... .... = Congestion Window Reduced (CWR): Not set\n\n\n.... .0.. .... = ECN-Echo: Not set\n\n\n.... ..0. .... = Urgent: Not set\n\n\n.... ...1 .... = Acknowledgment: Set\n\n\n.... .... 1... = Push: Set\n\n\n.... .... .0.. = Reset: Not set\n\n\n.... .... ..0. = Syn: Not set\n\n\n.... .... ...0 = Fin: Not set\n\n\nTCP Flags: \u00b7\u00b7\u00b7\u00b7\u00b7\u00b7\u00b7AP\u00b7\u00b7\u00b7\n\n\nWindow: 305\n\n\nCalculated window size: 305\n\n\nWindow size scaling factor: -1 (unknown)\n\n\nChecksum: 0x84d9 [unverified]\n\n\nChecksum Status: Unverified\n\n\nUrgent Pointer: 0\n\n\nSEQ/ACK analysis\n\n\nBytes in flight: 5632\n\n\nBytes sent since last PSH flag: 2816\n\n\nTimestamps\n\n\nTime since first frame in this TCP stream: 0.053478000 seconds\n\n\nTime since previous frame in this TCP stream: 0.000001000 seconds\n\n\nTCP payload (1408 bytes)\n\n\nTCP segment data (1408 bytes)\n\n\n"
        },
        {
            "lenght": "54",
            "Layer ETH": "\nDestination: 90:98:38:97:e0:a0\n\n\nAddress: 90:98:38:97:e0:a0\n\n\n.... ..0. .... .... .... .... = LG bit: Globally unique address (factory default)\n\n\n.... ...0 .... .... .... .... = IG bit: Individual address (unicast)\n\n\nSource: 44:39:c4:59:3b:02\n\n\n.... ..0. .... .... .... .... = LG bit: Globally unique address (factory default)\n\n\n.... ...0 .... .... .... .... = IG bit: Individual address (unicast)\n\n\nType: IPv4 (0x0800)\n\n\nAddress: 44:39:c4:59:3b:02\n\n\n",
            "Layer IP": "\n0100 .... = Version: 4\n\n\n.... 0101 = Header Length: 20 bytes (5)\n\n\nDifferentiated Services Field: 0x00 (DSCP: CS0, ECN: Not-ECT)\n\n\n0000 00.. = Differentiated Services Codepoint: Default (0)\n\n\n.... ..00 = Explicit Congestion Notification: Not ECN-Capable Transport (0)\n\n\nTotal Length: 40\n\n\nIdentification: 0xe981 (59777)\n\n\nFlags: 0x40, Don't fragment\n\n\n0... .... = Reserved bit: Not set\n\n\n.1.. .... = Don't fragment: Set\n\n\n..0. .... = More fragments: Not set\n\n\nFragment Offset: 0\n\n\nTime to Live: 128\n\n\nProtocol: TCP (6)\n\n\nHeader Checksum: 0x002c [validation disabled]\n\n\nHeader checksum status: Unverified\n\n\nSource Address: 192.168.1.147\n\n\nDestination Address: 74.125.4.106\n\n\n",
            "Layer TCP": "\nSource Port: 64378\n\n\nDestination Port: 443\n\n\nStream index: 1\n\n\nTCP Segment Len: 0\n\n\nSequence Number: 2233    (relative sequence number)\n\n\nSequence Number (raw): 1726352643\n\n\nNext Sequence Number: 2233    (relative sequence number)\n\n\nAcknowledgment Number: 5633    (relative ack number)\n\n\nAcknowledgment number (raw): 3692205333\n\n\n0101 .... = Header Length: 20 bytes (5)\n\n\nFlags: 0x010 (ACK)\n\n\n000. .... .... = Reserved: Not set\n\n\n...0 .... .... = Nonce: Not set\n\n\n.... 0... .... = Congestion Window Reduced (CWR): Not set\n\n\n.... .0.. .... = ECN-Echo: Not set\n\n\n.... ..0. .... = Urgent: Not set\n\n\n.... ...1 .... = Acknowledgment: Set\n\n\n.... .... 0... = Push: Not set\n\n\n.... .... .0.. = Reset: Not set\n\n\n.... .... ..0. = Syn: Not set\n\n\n.... .... ...0 = Fin: Not set\n\n\nTCP Flags: \u00b7\u00b7\u00b7\u00b7\u00b7\u00b7\u00b7A\u00b7\u00b7\u00b7\u00b7\n\n\nWindow: 517\n\n\nCalculated window size: 517\n\n\nWindow size scaling factor: -1 (unknown)\n\n\nChecksum: 0xba65 [unverified]\n\n\nChecksum Status: Unverified\n\n\nUrgent Pointer: 0\n\n\nSEQ/ACK analysis\n\n\nThis is an ACK to the segment in frame: 20\n\n\nThe RTT to ACK the segment was: 0.000165000 seconds\n\n\nTimestamps\n\n\nTime since first frame in this TCP stream: 0.053643000 seconds\n\n\nTime since previous frame in this TCP stream: 0.000165000 seconds\n\n\n"
        },
        {
            "lenght": "1462",
            "Layer ETH": "\nDestination: 44:39:c4:59:3b:02\n\n\nAddress: 44:39:c4:59:3b:02\n\n\n.... ..0. .... .... .... .... = LG bit: Globally unique address (factory default)\n\n\n.... ...0 .... .... .... .... = IG bit: Individual address (unicast)\n\n\nSource: 90:98:38:97:e0:a0\n\n\n.... ..0. .... .... .... .... = LG bit: Globally unique address (factory default)\n\n\n.... ...0 .... .... .... .... = IG bit: Individual address (unicast)\n\n\nType: IPv4 (0x0800)\n\n\nAddress: 90:98:38:97:e0:a0\n\n\n",
            "Layer IP": "\n0100 .... = Version: 4\n\n\n.... 0101 = Header Length: 20 bytes (5)\n\n\nDifferentiated Services Field: 0x00 (DSCP: CS0, ECN: Not-ECT)\n\n\n0000 00.. = Differentiated Services Codepoint: Default (0)\n\n\n.... ..00 = Explicit Congestion Notification: Not ECN-Capable Transport (0)\n\n\nTotal Length: 1448\n\n\nIdentification: 0x2594 (9620)\n\n\nFlags: 0x00\n\n\n0... .... = Reserved bit: Not set\n\n\n.0.. .... = Don't fragment: Not set\n\n\n..0. .... = More fragments: Not set\n\n\nFragment Offset: 0\n\n\nTime to Live: 57\n\n\nProtocol: TCP (6)\n\n\nHeader Checksum: 0x459a [validation disabled]\n\n\nHeader checksum status: Unverified\n\n\nSource Address: 74.125.4.106\n\n\nDestination Address: 192.168.1.147\n\n\n",
            "Layer TCP": "\nSource Port: 443\n\n\nDestination Port: 64378\n\n\nStream index: 1\n\n\nTCP Segment Len: 1408\n\n\nSequence Number: 5633    (relative sequence number)\n\n\nSequence Number (raw): 3692205333\n\n\nNext Sequence Number: 7041    (relative sequence number)\n\n\nAcknowledgment Number: 2233    (relative ack number)\n\n\nAcknowledgment number (raw): 1726352643\n\n\n0101 .... = Header Length: 20 bytes (5)\n\n\nFlags: 0x010 (ACK)\n\n\n000. .... .... = Reserved: Not set\n\n\n...0 .... .... = Nonce: Not set\n\n\n.... 0... .... = Congestion Window Reduced (CWR): Not set\n\n\n.... .0.. .... = ECN-Echo: Not set\n\n\n.... ..0. .... = Urgent: Not set\n\n\n.... ...1 .... = Acknowledgment: Set\n\n\n.... .... 0... = Push: Not set\n\n\n.... .... .0.. = Reset: Not set\n\n\n.... .... ..0. = Syn: Not set\n\n\n.... .... ...0 = Fin: Not set\n\n\nTCP Flags: \u00b7\u00b7\u00b7\u00b7\u00b7\u00b7\u00b7A\u00b7\u00b7\u00b7\u00b7\n\n\nWindow: 305\n\n\nCalculated window size: 305\n\n\nWindow size scaling factor: -1 (unknown)\n\n\nChecksum: 0xf995 [unverified]\n\n\nChecksum Status: Unverified\n\n\nUrgent Pointer: 0\n\n\nSEQ/ACK analysis\n\n\nBytes in flight: 1408\n\n\nBytes sent since last PSH flag: 1408\n\n\nTimestamps\n\n\nTime since first frame in this TCP stream: 0.055125000 seconds\n\n\nTime since previous frame in this TCP stream: 0.001482000 seconds\n\n\nTCP payload (1408 bytes)\n\n\nTCP segment data (1408 bytes)\n\n\n"
        },
        {
            "lenght": "1462",
            "Layer ETH": "\nDestination: 44:39:c4:59:3b:02\n\n\nAddress: 44:39:c4:59:3b:02\n\n\n.... ..0. .... .... .... .... = LG bit: Globally unique address (factory default)\n\n\n.... ...0 .... .... .... .... = IG bit: Individual address (unicast)\n\n\nSource: 90:98:38:97:e0:a0\n\n\n.... ..0. .... .... .... .... = LG bit: Globally unique address (factory default)\n\n\n.... ...0 .... .... .... .... = IG bit: Individual address (unicast)\n\n\nType: IPv4 (0x0800)\n\n\nAddress: 90:98:38:97:e0:a0\n\n\n",
            "Layer IP": "\n0100 .... = Version: 4\n\n\n.... 0101 = Header Length: 20 bytes (5)\n\n\nDifferentiated Services Field: 0x00 (DSCP: CS0, ECN: Not-ECT)\n\n\n0000 00.. = Differentiated Services Codepoint: Default (0)\n\n\n.... ..00 = Explicit Congestion Notification: Not ECN-Capable Transport (0)\n\n\nTotal Length: 1448\n\n\nIdentification: 0x2595 (9621)\n\n\nFlags: 0x00\n\n\n0... .... = Reserved bit: Not set\n\n\n.0.. .... = Don't fragment: Not set\n\n\n..0. .... = More fragments: Not set\n\n\nFragment Offset: 0\n\n\nTime to Live: 57\n\n\nProtocol: TCP (6)\n\n\nHeader Checksum: 0x4599 [validation disabled]\n\n\nHeader checksum status: Unverified\n\n\nSource Address: 74.125.4.106\n\n\nDestination Address: 192.168.1.147\n\n\n",
            "Layer TCP": "\nSource Port: 443\n\n\nDestination Port: 64378\n\n\nStream index: 1\n\n\nTCP Segment Len: 1408\n\n\nSequence Number: 7041    (relative sequence number)\n\n\nSequence Number (raw): 3692206741\n\n\nNext Sequence Number: 8449    (relative sequence number)\n\n\nAcknowledgment Number: 2233    (relative ack number)\n\n\nAcknowledgment number (raw): 1726352643\n\n\n0101 .... = Header Length: 20 bytes (5)\n\n\nFlags: 0x018 (PSH, ACK)\n\n\n000. .... .... = Reserved: Not set\n\n\n...0 .... .... = Nonce: Not set\n\n\n.... 0... .... = Congestion Window Reduced (CWR): Not set\n\n\n.... .0.. .... = ECN-Echo: Not set\n\n\n.... ..0. .... = Urgent: Not set\n\n\n.... ...1 .... = Acknowledgment: Set\n\n\n.... .... 1... = Push: Set\n\n\n.... .... .0.. = Reset: Not set\n\n\n.... .... ..0. = Syn: Not set\n\n\n.... .... ...0 = Fin: Not set\n\n\nTCP Flags: \u00b7\u00b7\u00b7\u00b7\u00b7\u00b7\u00b7AP\u00b7\u00b7\u00b7\n\n\nWindow: 305\n\n\nCalculated window size: 305\n\n\nWindow size scaling factor: -1 (unknown)\n\n\nChecksum: 0x31ec [unverified]\n\n\nChecksum Status: Unverified\n\n\nUrgent Pointer: 0\n\n\nSEQ/ACK analysis\n\n\nBytes in flight: 2816\n\n\nBytes sent since last PSH flag: 2816\n\n\nTimestamps\n\n\nTime since first frame in this TCP stream: 0.055126000 seconds\n\n\nTime since previous frame in this TCP stream: 0.000001000 seconds\n\n\nTCP payload (1408 bytes)\n\n\nTCP segment data (1408 bytes)\n\n\n"
        },
        {
            "lenght": "54",
            "Layer ETH": "\nDestination: 90:98:38:97:e0:a0\n\n\nAddress: 90:98:38:97:e0:a0\n\n\n.... ..0. .... .... .... .... = LG bit: Globally unique address (factory default)\n\n\n.... ...0 .... .... .... .... = IG bit: Individual address (unicast)\n\n\nSource: 44:39:c4:59:3b:02\n\n\n.... ..0. .... .... .... .... = LG bit: Globally unique address (factory default)\n\n\n.... ...0 .... .... .... .... = IG bit: Individual address (unicast)\n\n\nType: IPv4 (0x0800)\n\n\nAddress: 44:39:c4:59:3b:02\n\n\n",
            "Layer IP": "\n0100 .... = Version: 4\n\n\n.... 0101 = Header Length: 20 bytes (5)\n\n\nDifferentiated Services Field: 0x00 (DSCP: CS0, ECN: Not-ECT)\n\n\n0000 00.. = Differentiated Services Codepoint: Default (0)\n\n\n.... ..00 = Explicit Congestion Notification: Not ECN-Capable Transport (0)\n\n\nTotal Length: 40\n\n\nIdentification: 0xe982 (59778)\n\n\nFlags: 0x40, Don't fragment\n\n\n0... .... = Reserved bit: Not set\n\n\n.1.. .... = Don't fragment: Set\n\n\n..0. .... = More fragments: Not set\n\n\nFragment Offset: 0\n\n\nTime to Live: 128\n\n\nProtocol: TCP (6)\n\n\nHeader Checksum: 0x002b [validation disabled]\n\n\nHeader checksum status: Unverified\n\n\nSource Address: 192.168.1.147\n\n\nDestination Address: 74.125.4.106\n\n\n",
            "Layer TCP": "\nSource Port: 64378\n\n\nDestination Port: 443\n\n\nStream index: 1\n\n\nTCP Segment Len: 0\n\n\nSequence Number: 2233    (relative sequence number)\n\n\nSequence Number (raw): 1726352643\n\n\nNext Sequence Number: 2233    (relative sequence number)\n\n\nAcknowledgment Number: 8449    (relative ack number)\n\n\nAcknowledgment number (raw): 3692208149\n\n\n0101 .... = Header Length: 20 bytes (5)\n\n\nFlags: 0x010 (ACK)\n\n\n000. .... .... = Reserved: Not set\n\n\n...0 .... .... = Nonce: Not set\n\n\n.... 0... .... = Congestion Window Reduced (CWR): Not set\n\n\n.... .0.. .... = ECN-Echo: Not set\n\n\n.... ..0. .... = Urgent: Not set\n\n\n.... ...1 .... = Acknowledgment: Set\n\n\n.... .... 0... = Push: Not set\n\n\n.... .... .0.. = Reset: Not set\n\n\n.... .... ..0. = Syn: Not set\n\n\n.... .... ...0 = Fin: Not set\n\n\nTCP Flags: \u00b7\u00b7\u00b7\u00b7\u00b7\u00b7\u00b7A\u00b7\u00b7\u00b7\u00b7\n\n\nWindow: 517\n\n\nCalculated window size: 517\n\n\nWindow size scaling factor: -1 (unknown)\n\n\nChecksum: 0xaf65 [unverified]\n\n\nChecksum Status: Unverified\n\n\nUrgent Pointer: 0\n\n\nSEQ/ACK analysis\n\n\nThis is an ACK to the segment in frame: 23\n\n\nThe RTT to ACK the segment was: 0.000095000 seconds\n\n\nTimestamps\n\n\nTime since first frame in this TCP stream: 0.055221000 seconds\n\n\nTime since previous frame in this TCP stream: 0.000095000 seconds\n\n\n"
        },
        {
            "lenght": "1462",
            "Layer ETH": "\nDestination: 44:39:c4:59:3b:02\n\n\nAddress: 44:39:c4:59:3b:02\n\n\n.... ..0. .... .... .... .... = LG bit: Globally unique address (factory default)\n\n\n.... ...0 .... .... .... .... = IG bit: Individual address (unicast)\n\n\nSource: 90:98:38:97:e0:a0\n\n\n.... ..0. .... .... .... .... = LG bit: Globally unique address (factory default)\n\n\n.... ...0 .... .... .... .... = IG bit: Individual address (unicast)\n\n\nType: IPv4 (0x0800)\n\n\nAddress: 90:98:38:97:e0:a0\n\n\n",
            "Layer IP": "\n0100 .... = Version: 4\n\n\n.... 0101 = Header Length: 20 bytes (5)\n\n\nDifferentiated Services Field: 0x00 (DSCP: CS0, ECN: Not-ECT)\n\n\n0000 00.. = Differentiated Services Codepoint: Default (0)\n\n\n.... ..00 = Explicit Congestion Notification: Not ECN-Capable Transport (0)\n\n\nTotal Length: 1448\n\n\nIdentification: 0x2596 (9622)\n\n\nFlags: 0x00\n\n\n0... .... = Reserved bit: Not set\n\n\n.0.. .... = Don't fragment: Not set\n\n\n..0. .... = More fragments: Not set\n\n\nFragment Offset: 0\n\n\nTime to Live: 57\n\n\nProtocol: TCP (6)\n\n\nHeader Checksum: 0x4598 [validation disabled]\n\n\nHeader checksum status: Unverified\n\n\nSource Address: 74.125.4.106\n\n\nDestination Address: 192.168.1.147\n\n\n",
            "Layer TCP": "\nSource Port: 443\n\n\nDestination Port: 64378\n\n\nStream index: 1\n\n\nTCP Segment Len: 1408\n\n\nSequence Number: 8449    (relative sequence number)\n\n\nSequence Number (raw): 3692208149\n\n\nNext Sequence Number: 9857    (relative sequence number)\n\n\nAcknowledgment Number: 2233    (relative ack number)\n\n\nAcknowledgment number (raw): 1726352643\n\n\n0101 .... = Header Length: 20 bytes (5)\n\n\nFlags: 0x010 (ACK)\n\n\n000. .... .... = Reserved: Not set\n\n\n...0 .... .... = Nonce: Not set\n\n\n.... 0... .... = Congestion Window Reduced (CWR): Not set\n\n\n.... .0.. .... = ECN-Echo: Not set\n\n\n.... ..0. .... = Urgent: Not set\n\n\n.... ...1 .... = Acknowledgment: Set\n\n\n.... .... 0... = Push: Not set\n\n\n.... .... .0.. = Reset: Not set\n\n\n.... .... ..0. = Syn: Not set\n\n\n.... .... ...0 = Fin: Not set\n\n\nTCP Flags: \u00b7\u00b7\u00b7\u00b7\u00b7\u00b7\u00b7A\u00b7\u00b7\u00b7\u00b7\n\n\nWindow: 305\n\n\nCalculated window size: 305\n\n\nWindow size scaling factor: -1 (unknown)\n\n\nChecksum: 0x3cce [unverified]\n\n\nChecksum Status: Unverified\n\n\nUrgent Pointer: 0\n\n\nSEQ/ACK analysis\n\n\nBytes in flight: 1408\n\n\nBytes sent since last PSH flag: 1408\n\n\nTimestamps\n\n\nTime since first frame in this TCP stream: 0.057307000 seconds\n\n\nTime since previous frame in this TCP stream: 0.002086000 seconds\n\n\nTCP payload (1408 bytes)\n\n\nTCP segment data (1408 bytes)\n\n\n"
        },
        {
            "lenght": "1462",
            "Layer ETH": "\nDestination: 44:39:c4:59:3b:02\n\n\nAddress: 44:39:c4:59:3b:02\n\n\n.... ..0. .... .... .... .... = LG bit: Globally unique address (factory default)\n\n\n.... ...0 .... .... .... .... = IG bit: Individual address (unicast)\n\n\nSource: 90:98:38:97:e0:a0\n\n\n.... ..0. .... .... .... .... = LG bit: Globally unique address (factory default)\n\n\n.... ...0 .... .... .... .... = IG bit: Individual address (unicast)\n\n\nType: IPv4 (0x0800)\n\n\nAddress: 90:98:38:97:e0:a0\n\n\n",
            "Layer IP": "\n0100 .... = Version: 4\n\n\n.... 0101 = Header Length: 20 bytes (5)\n\n\nDifferentiated Services Field: 0x00 (DSCP: CS0, ECN: Not-ECT)\n\n\n0000 00.. = Differentiated Services Codepoint: Default (0)\n\n\n.... ..00 = Explicit Congestion Notification: Not ECN-Capable Transport (0)\n\n\nTotal Length: 1448\n\n\nIdentification: 0x2597 (9623)\n\n\nFlags: 0x00\n\n\n0... .... = Reserved bit: Not set\n\n\n.0.. .... = Don't fragment: Not set\n\n\n..0. .... = More fragments: Not set\n\n\nFragment Offset: 0\n\n\nTime to Live: 57\n\n\nProtocol: TCP (6)\n\n\nHeader Checksum: 0x4597 [validation disabled]\n\n\nHeader checksum status: Unverified\n\n\nSource Address: 74.125.4.106\n\n\nDestination Address: 192.168.1.147\n\n\n",
            "Layer TCP": "\nSource Port: 443\n\n\nDestination Port: 64378\n\n\nStream index: 1\n\n\nTCP Segment Len: 1408\n\n\nSequence Number: 9857    (relative sequence number)\n\n\nSequence Number (raw): 3692209557\n\n\nNext Sequence Number: 11265    (relative sequence number)\n\n\nAcknowledgment Number: 2233    (relative ack number)\n\n\nAcknowledgment number (raw): 1726352643\n\n\n0101 .... = Header Length: 20 bytes (5)\n\n\nFlags: 0x018 (PSH, ACK)\n\n\n000. .... .... = Reserved: Not set\n\n\n...0 .... .... = Nonce: Not set\n\n\n.... 0... .... = Congestion Window Reduced (CWR): Not set\n\n\n.... .0.. .... = ECN-Echo: Not set\n\n\n.... ..0. .... = Urgent: Not set\n\n\n.... ...1 .... = Acknowledgment: Set\n\n\n.... .... 1... = Push: Set\n\n\n.... .... .0.. = Reset: Not set\n\n\n.... .... ..0. = Syn: Not set\n\n\n.... .... ...0 = Fin: Not set\n\n\nTCP Flags: \u00b7\u00b7\u00b7\u00b7\u00b7\u00b7\u00b7AP\u00b7\u00b7\u00b7\n\n\nWindow: 305\n\n\nCalculated window size: 305\n\n\nWindow size scaling factor: -1 (unknown)\n\n\nChecksum: 0x53f9 [unverified]\n\n\nChecksum Status: Unverified\n\n\nUrgent Pointer: 0\n\n\nSEQ/ACK analysis\n\n\nBytes in flight: 2816\n\n\nBytes sent since last PSH flag: 2816\n\n\nTimestamps\n\n\nTime since first frame in this TCP stream: 0.057307000 seconds\n\n\nTime since previous frame in this TCP stream: 0.000000000 seconds\n\n\nTCP payload (1408 bytes)\n\n\nTCP segment data (1408 bytes)\n\n\n"
        },
        {
            "lenght": "1462",
            "Layer ETH": "\nDestination: 44:39:c4:59:3b:02\n\n\nAddress: 44:39:c4:59:3b:02\n\n\n.... ..0. .... .... .... .... = LG bit: Globally unique address (factory default)\n\n\n.... ...0 .... .... .... .... = IG bit: Individual address (unicast)\n\n\nSource: 90:98:38:97:e0:a0\n\n\n.... ..0. .... .... .... .... = LG bit: Globally unique address (factory default)\n\n\n.... ...0 .... .... .... .... = IG bit: Individual address (unicast)\n\n\nType: IPv4 (0x0800)\n\n\nAddress: 90:98:38:97:e0:a0\n\n\n",
            "Layer IP": "\n0100 .... = Version: 4\n\n\n.... 0101 = Header Length: 20 bytes (5)\n\n\nDifferentiated Services Field: 0x00 (DSCP: CS0, ECN: Not-ECT)\n\n\n0000 00.. = Differentiated Services Codepoint: Default (0)\n\n\n.... ..00 = Explicit Congestion Notification: Not ECN-Capable Transport (0)\n\n\nTotal Length: 1448\n\n\nIdentification: 0x2598 (9624)\n\n\nFlags: 0x00\n\n\n0... .... = Reserved bit: Not set\n\n\n.0.. .... = Don't fragment: Not set\n\n\n..0. .... = More fragments: Not set\n\n\nFragment Offset: 0\n\n\nTime to Live: 57\n\n\nProtocol: TCP (6)\n\n\nHeader Checksum: 0x4596 [validation disabled]\n\n\nHeader checksum status: Unverified\n\n\nSource Address: 74.125.4.106\n\n\nDestination Address: 192.168.1.147\n\n\n",
            "Layer TCP": "\nSource Port: 443\n\n\nDestination Port: 64378\n\n\nStream index: 1\n\n\nTCP Segment Len: 1408\n\n\nSequence Number: 11265    (relative sequence number)\n\n\nSequence Number (raw): 3692210965\n\n\nNext Sequence Number: 12673    (relative sequence number)\n\n\nAcknowledgment Number: 2233    (relative ack number)\n\n\nAcknowledgment number (raw): 1726352643\n\n\n0101 .... = Header Length: 20 bytes (5)\n\n\nFlags: 0x010 (ACK)\n\n\n000. .... .... = Reserved: Not set\n\n\n...0 .... .... = Nonce: Not set\n\n\n.... 0... .... = Congestion Window Reduced (CWR): Not set\n\n\n.... .0.. .... = ECN-Echo: Not set\n\n\n.... ..0. .... = Urgent: Not set\n\n\n.... ...1 .... = Acknowledgment: Set\n\n\n.... .... 0... = Push: Not set\n\n\n.... .... .0.. = Reset: Not set\n\n\n.... .... ..0. = Syn: Not set\n\n\n.... .... ...0 = Fin: Not set\n\n\nTCP Flags: \u00b7\u00b7\u00b7\u00b7\u00b7\u00b7\u00b7A\u00b7\u00b7\u00b7\u00b7\n\n\nWindow: 305\n\n\nCalculated window size: 305\n\n\nWindow size scaling factor: -1 (unknown)\n\n\nChecksum: 0x9f04 [unverified]\n\n\nChecksum Status: Unverified\n\n\nUrgent Pointer: 0\n\n\nSEQ/ACK analysis\n\n\nBytes in flight: 4224\n\n\nBytes sent since last PSH flag: 1408\n\n\nTimestamps\n\n\nTime since first frame in this TCP stream: 0.057308000 seconds\n\n\nTime since previous frame in this TCP stream: 0.000001000 seconds\n\n\nTCP payload (1408 bytes)\n\n\nTCP segment data (1408 bytes)\n\n\n"
        },
        {
            "lenght": "1462",
            "Layer ETH": "\nDestination: 44:39:c4:59:3b:02\n\n\nAddress: 44:39:c4:59:3b:02\n\n\n.... ..0. .... .... .... .... = LG bit: Globally unique address (factory default)\n\n\n.... ...0 .... .... .... .... = IG bit: Individual address (unicast)\n\n\nSource: 90:98:38:97:e0:a0\n\n\n.... ..0. .... .... .... .... = LG bit: Globally unique address (factory default)\n\n\n.... ...0 .... .... .... .... = IG bit: Individual address (unicast)\n\n\nType: IPv4 (0x0800)\n\n\nAddress: 90:98:38:97:e0:a0\n\n\n",
            "Layer IP": "\n0100 .... = Version: 4\n\n\n.... 0101 = Header Length: 20 bytes (5)\n\n\nDifferentiated Services Field: 0x00 (DSCP: CS0, ECN: Not-ECT)\n\n\n0000 00.. = Differentiated Services Codepoint: Default (0)\n\n\n.... ..00 = Explicit Congestion Notification: Not ECN-Capable Transport (0)\n\n\nTotal Length: 1448\n\n\nIdentification: 0x2599 (9625)\n\n\nFlags: 0x00\n\n\n0... .... = Reserved bit: Not set\n\n\n.0.. .... = Don't fragment: Not set\n\n\n..0. .... = More fragments: Not set\n\n\nFragment Offset: 0\n\n\nTime to Live: 57\n\n\nProtocol: TCP (6)\n\n\nHeader Checksum: 0x4595 [validation disabled]\n\n\nHeader checksum status: Unverified\n\n\nSource Address: 74.125.4.106\n\n\nDestination Address: 192.168.1.147\n\n\n",
            "Layer TCP": "\nSource Port: 443\n\n\nDestination Port: 64378\n\n\nStream index: 1\n\n\nTCP Segment Len: 1408\n\n\nSequence Number: 12673    (relative sequence number)\n\n\nSequence Number (raw): 3692212373\n\n\nNext Sequence Number: 14081    (relative sequence number)\n\n\nAcknowledgment Number: 2233    (relative ack number)\n\n\nAcknowledgment number (raw): 1726352643\n\n\n0101 .... = Header Length: 20 bytes (5)\n\n\nFlags: 0x018 (PSH, ACK)\n\n\n000. .... .... = Reserved: Not set\n\n\n...0 .... .... = Nonce: Not set\n\n\n.... 0... .... = Congestion Window Reduced (CWR): Not set\n\n\n.... .0.. .... = ECN-Echo: Not set\n\n\n.... ..0. .... = Urgent: Not set\n\n\n.... ...1 .... = Acknowledgment: Set\n\n\n.... .... 1... = Push: Set\n\n\n.... .... .0.. = Reset: Not set\n\n\n.... .... ..0. = Syn: Not set\n\n\n.... .... ...0 = Fin: Not set\n\n\nTCP Flags: \u00b7\u00b7\u00b7\u00b7\u00b7\u00b7\u00b7AP\u00b7\u00b7\u00b7\n\n\nWindow: 305\n\n\nCalculated window size: 305\n\n\nWindow size scaling factor: -1 (unknown)\n\n\nChecksum: 0x8417 [unverified]\n\n\nChecksum Status: Unverified\n\n\nUrgent Pointer: 0\n\n\nSEQ/ACK analysis\n\n\nBytes in flight: 5632\n\n\nBytes sent since last PSH flag: 2816\n\n\nTimestamps\n\n\nTime since first frame in this TCP stream: 0.057309000 seconds\n\n\nTime since previous frame in this TCP stream: 0.000001000 seconds\n\n\nTCP payload (1408 bytes)\n\n\nTCP segment data (1408 bytes)\n\n\n"
        },
        {
            "lenght": "54",
            "Layer ETH": "\nDestination: 90:98:38:97:e0:a0\n\n\nAddress: 90:98:38:97:e0:a0\n\n\n.... ..0. .... .... .... .... = LG bit: Globally unique address (factory default)\n\n\n.... ...0 .... .... .... .... = IG bit: Individual address (unicast)\n\n\nSource: 44:39:c4:59:3b:02\n\n\n.... ..0. .... .... .... .... = LG bit: Globally unique address (factory default)\n\n\n.... ...0 .... .... .... .... = IG bit: Individual address (unicast)\n\n\nType: IPv4 (0x0800)\n\n\nAddress: 44:39:c4:59:3b:02\n\n\n",
            "Layer IP": "\n0100 .... = Version: 4\n\n\n.... 0101 = Header Length: 20 bytes (5)\n\n\nDifferentiated Services Field: 0x00 (DSCP: CS0, ECN: Not-ECT)\n\n\n0000 00.. = Differentiated Services Codepoint: Default (0)\n\n\n.... ..00 = Explicit Congestion Notification: Not ECN-Capable Transport (0)\n\n\nTotal Length: 40\n\n\nIdentification: 0xe983 (59779)\n\n\nFlags: 0x40, Don't fragment\n\n\n0... .... = Reserved bit: Not set\n\n\n.1.. .... = Don't fragment: Set\n\n\n..0. .... = More fragments: Not set\n\n\nFragment Offset: 0\n\n\nTime to Live: 128\n\n\nProtocol: TCP (6)\n\n\nHeader Checksum: 0x002a [validation disabled]\n\n\nHeader checksum status: Unverified\n\n\nSource Address: 192.168.1.147\n\n\nDestination Address: 74.125.4.106\n\n\n",
            "Layer TCP": "\nSource Port: 64378\n\n\nDestination Port: 443\n\n\nStream index: 1\n\n\nTCP Segment Len: 0\n\n\nSequence Number: 2233    (relative sequence number)\n\n\nSequence Number (raw): 1726352643\n\n\nNext Sequence Number: 2233    (relative sequence number)\n\n\nAcknowledgment Number: 14081    (relative ack number)\n\n\nAcknowledgment number (raw): 3692213781\n\n\n0101 .... = Header Length: 20 bytes (5)\n\n\nFlags: 0x010 (ACK)\n\n\n000. .... .... = Reserved: Not set\n\n\n...0 .... .... = Nonce: Not set\n\n\n.... 0... .... = Congestion Window Reduced (CWR): Not set\n\n\n.... .0.. .... = ECN-Echo: Not set\n\n\n.... ..0. .... = Urgent: Not set\n\n\n.... ...1 .... = Acknowledgment: Set\n\n\n.... .... 0... = Push: Not set\n\n\n.... .... .0.. = Reset: Not set\n\n\n.... .... ..0. = Syn: Not set\n\n\n.... .... ...0 = Fin: Not set\n\n\nTCP Flags: \u00b7\u00b7\u00b7\u00b7\u00b7\u00b7\u00b7A\u00b7\u00b7\u00b7\u00b7\n\n\nWindow: 517\n\n\nCalculated window size: 517\n\n\nWindow size scaling factor: -1 (unknown)\n\n\nChecksum: 0x9965 [unverified]\n\n\nChecksum Status: Unverified\n\n\nUrgent Pointer: 0\n\n\nSEQ/ACK analysis\n\n\nThis is an ACK to the segment in frame: 28\n\n\nThe RTT to ACK the segment was: 0.000131000 seconds\n\n\nTimestamps\n\n\nTime since first frame in this TCP stream: 0.057440000 seconds\n\n\nTime since previous frame in this TCP stream: 0.000131000 seconds\n\n\n"
        }
    ]
}